Workbook

Sheet 00_COVER
A1: Denmark: Digital Adoption and Policy Outcomes
A2: Statistical annex to Assessment 2 - Digital Policy and Innovation Report
A4: Student ID | B4: s4040040
A5: Course | B5: ECON1596/ECON1597 Digital Economy and Policy
A6: Assessment | B6: Assessment 2 - Digital Policy and Innovation Report
A7: Country | B7: Denmark (assigned by final digit of student ID: 0)
A8: Workbook version | B8: 1.0
A9: Built | B9: 2026-09-12
A10: Observations | B10: 113
A11: Coverage | B11: 1991-2026, unbalanced; see 07_LIMITATIONS
A13: Suggested citation | B13: Denmark: Digital Adoption and Policy Outcomes [data workbook], v1.0, 2026-09-12. Compiled from the sources listed in 03_SOURCES.
A15: Provenance rule | B15: Every value in this workbook was verified against the issuing authority named in its source_id. No value is interpolated, smoothed, or inferred from a neighbouring year. Gaps are left as gaps.
A16: Structure rule | B16: 02_MASTER is the single source of truth. Every figure sheet and every derived quantity is a formula view of it, not a pasted copy.
A18: CONTENTS
A19: 01_README | B19: Conventions, flag legend, how to trace any value
A20: 02_MASTER | B20: Every observation, one row each
A21: 03_SOURCES | B21: Source register with URLs, access dates, Harvard references
A22: 04_DEFINITIONS | B22: What each indicator measures, and what it excludes
A23: 05_CALC | B23: Derived quantities, as live formulas
A24: F1_BRANCHES | B24: Figure 1 - bank branch network, 2004-2024
A25: F2_PAYMENTS | B25: Figure 2 - payment instrument shares, 2017-2025
A26: F3_ESALES | B26: Figure 3 - e-sales share of turnover, DK vs EU
A27: F4_EXCLUSION | B27: Figure 4 - measures of digital exclusion
A28: F5_EU27 | B28: Figure 5 - online purchasing, all 27 member states, 2024
A29: F6_ADOPT_BENEFIT | B29: Figure 6 - adoption vs economic effect, EU 2024
A30: F7_QUALITY | B30: Figure 7 - DK vs EU: leads on adoption, trails on service quality
... A37: 08_AI_LOG | B37: AI use and validation log

Sheet 01_README
A1: How to read this workbook
A4: PURPOSE | B4: This workbook is the raw-data attachment to a 2,000-word policy report on Denmark's digital transformation. It is designed so that any number appearing in the report can be traced to an issuing authority, a denominator and an access date without consulting the author.
A5: TRACING A VALUE | B5: 1. Find the value on a figure sheet. 2. Read its series_code. 3. Filter 02_MASTER by that series_code to find the observation row. 4. Take its source_id to 03_SOURCES for the authority, URL and access date. 5. Check 04_DEFINITIONS for what the indicator does and does not cover.
A6: SINGLE SOURCE OF TRUTH | B6: 02_MASTER holds every observation. Figure sheets contain no typed numbers - each cell is a COUNTIFS/SUMIFS lookup against 02_MASTER. Correcting a value in 02_MASTER updates every sheet and chart that uses it.
A7: DENOMINATORS | B7: The denominator column in 02_MASTER is load-bearing, not decorative. Eurostat's Danish online-purchasing figures change base between 2019 (% of individuals) and 2020 onward (% of internet users). Series with different denominators are never plotted on one axis.
A9: FLAG LEGEND
A10: Flag | B10: Meaning
A11: b | B11: Break in series - definition or denominator changed. Do not plot across.
A12: e | B12: Estimate - source gives an approximation or a verbal quantity.
A13: p | B13: Provisional.
A14: d | B14: Definition differs from the rest of the series.
A15: u | B15: Low reliability.
A16: (blank) | B16: Value as published, no qualification.
A18: COLOUR LEGEND
B19: Retrieved value - as published by the source
B20: Derived - calculated by formula from retrieved values
B21: Flagged - estimate, break, or otherwise qualified
B22: Documented gap - value not retrieved
A25: BEFORE CITING | B25: Read 07_LIMITATIONS. Several series have very few observations and none supports inferential statistics.

Sheet 02_MASTER
A1: obs_id | B1: series_code | C1: indicator | D1: geo | E1: year | F1: value | G1: unit | H1: denominator | I1: flag | J1: source_id | K1: extraction_date | L1: notes
A2: 1 | B2: DK.PAY.CASH.POS | C2: Cash share of payments, physical retail | D2: DK | E2: 2017 | F2: 23 | G2: % | H2: share of number of payments in physical retail | J2: NB1 | K2: 2026-09-12
A3: 2 | B3: DK.PAY.CASH.POS | C3: Cash share of payments, physical retail | D3: DK | E3: 2023 | F3: 11 | G3: % | H3: share of number of payments in physical retail | J3: NB1 | K3: 2026-09-12
A4: 3 | B4: DK.PAY.CASH.POS | C4: Cash share of payments, physical retail | D4: DK | E4: 2025 | F4: 9 | G4: % | H4: share of number of payments in physical retail | J4: NB1 | K4: 2026-09-12
A5: 4 | B5: DK.PAY.CRD.PHYS | C5: Physical payment card share of payments | D5: DK | E5: 2017 | F5: 73 | G5: % | H5: share of number of payments in physical retail | J5: NB1 | K5: 2026-09-12
A6: 5 | B6: DK.PAY.CRD.PHYS | C6: Physical payment card share of payments | D6: DK | E6: 2025 | F6: 54 | G6: % | H6: share of number of payments in physical retail | J6: NB1 | K6: 2026-09-12
A7: 6 | B7: DK.PAY.WLT.SHR | C7: Mobile wallet share of payments | D7: DK | E7: 2025 | F7: 32 | G7: % | H7: share of number of payments in physical retail | J7: NB1 | K7: 2026-09-12 | L7: Card-based wallets on mobile phones (e.g. Apple Pay, Google Pay).
A8: 7 | B8: DK.PAY.DIG.POS.NUM | C8: Digital share of payments, by number | D8: DK | E8: 2025 | F8: 91 | G8: % | H8: share of number of payments in physical retail | J8: NB1 | K8: 2026-09-12
A9: 8 | B9: DK.PAY.DIG.POS.VAL | C9: Digital share of payments, by value | D9: DK | E9: 2025 | F9: 93 | G9: % | H9: share of value of payments in physical retail | J9: NB1 | K9: 2026-09-12 | L9: Different denominator from the by-number series - do not plot together.
A10: 9 | B10: DK.PAY.WLT.OWN | C10: Citizens holding a mobile wallet solution | D10: DK | E10: 2019 | F10: 12 | G10: % | H10: % of citizens | J10: NB1 | K10: 2026-09-12 | L10: Memo only - denominator differs from F2 series.
A11: 10 | B11: DK.PAY.WLT.OWN | C11: Citizens holding a mobile wallet solution | D11: DK | E11: 2023 | F11: 41 | G11: % | H11: % of citizens | J11: NB1 | K11: 2026-09-12 | L11: Memo only - denominator differs from F2 series.
A12: 11 | B12: DK.PAY.WLT.OWN | C12: Citizens holding a mobile wallet solution | D12: DK | E12: 2025 | F12: 51 | G12: % | H12: % of citizens | J12: NB1 | K12: 2026-09-12 | L12: Memo only - denominator differs from F2 series.
A13: 12 | B13: DK.FIN.BRCH | C13: Bank branches | D13: DK | E13: 2004 | F13: 2025 | G13: count | H13: branches | J13: FD1 | K13: 2026-09-12
A14: 13 | B14: DK.FIN.BRCH | C14: Bank branches | D14: DK | E14: 2006 | F14: 1975 | G14: count | H14: branches | J14: FD1 | K14: 2026-09-12
A15: 14 | B15: DK.FIN.BRCH | C15: Bank branches | D15: DK | E15: 2010 | F15: 1598 | G15: count | H15: branches | J15: FD1 | K15: 2026-09-12
A16: 15 | B16: DK.FIN.BRCH | C16: Bank branches | D16: DK | E16: 2016 | F16: 948 | G16: count | H16: branches | J16: FD1 | K16: 2026-09-12
A17: 16 | B17: DK.FIN.BRCH | C17: Bank branches | D17: DK | E17: 2021 | F17: 701 | G17: count | H17: branches | J17: FD1 | K17: 2026-09-12
A18: 17 | B18: DK.FIN.BRCH | C18: Bank branches | D18: DK | E18: 2024 | F18: 665 | G18: count | H18: branches | J18: FD1 | K18: 2026-09-12
A19: 18 | B19: DK.FIN.INST | C19: Financial institutions | D19: DK | E19: 1991 | F19: 219 | G19: count | H19: institutions | J19: FD1 | K19: 2026-09-12
A20: 19 | B20: DK.FIN.INST | C20: Financial institutions | D20: DK | E20: 2024 | F20: 51 | G20: count | H20: institutions | J20: FD1 | K20: 2026-09-12
A21: 20 | B21: DK.FIN.EMP | C21: Bank employees | D21: DK | E21: 1991 | F21: 51000 | G21: count | H21: persons employed | I21: e | J21: FD1 | K21: 2026-09-12 | L21: Source states 'around 51,000'.
A22: 21 | B22: DK.FIN.EMP | C22: Bank employees | D22: DK | E22: 2024 | F22: 36000 | G22: count | H22: persons employed | I22: e | J22: FD1 | K22: 2026-09-12 | L22: Source states 'just under 36,000'.
A23: 22 | B23: DK.ECM.IND.BUY | C23: Individuals who bought online in last 12 months | D23: DK | E23: 2019 | F23: 84 | G23: % | H23: % of individuals | I23: b | J23: ES1 | K23: 2026-09-12 | L23: BREAK: denominator is % of individuals. Highest in EU that year.
A24: 23 | B24: DK.ECM.IND.BUY | C24: Individuals who bought online in last 12 months | D24: DK | E24: 2020 | F24: 90 | G24: % | H24: % of internet users | J24: ES2 | K24: 2026-09-12 | L24: Rounded, from a Eurostat news release. Only the 2024 cross-section is available here unrounded, so this series mixes precisions across years.
A25: 24 | B25: DK.ECM.IND.BUY | C25: Individuals who bought online in last 12 months | D25: DK | E25: 2021 | F25: 92 | G25: % | H25: % of internet users | J25: ES3 | K25: 2026-09-12 | L25: Rounded, from a Eurostat news release. See the 2020 note on mixed precision.
A26: 25 | B26: EU.ECM.IND.BUY | C26: Individuals who bought online in last 12 months | D26: EU27 | E26: 2024 | F26: 76.58 | G26: % | H26: % of internet users | J26: ES7 | K26: 2026-09-12
A27: 26 | B27: AT.ECM.IND.BUY | C27: Individuals who bought online in last 12 months | D27: AT | E27: 2024 | F27: 74.18 | G27: % | H27: % of internet users | J27: ES7 | K27: 2026-09-12
A28: 27 | B28: BE.ECM.IND.BUY | C28: Individuals who bought online in last 12 months | D28: BE | E28: 2024 | F28: 78.98 | G28: % | H28: % of internet users | J28: ES7 | K28: 2026-09-12
A29: 28 | B29: BG.ECM.IND.BUY | C29: Individuals who bought online in last 12 months | D29: BG | E29: 2024 | F29: 57.18 | G29: % | H29: % of internet users | J29: ES7 | K29: 2026-09-12 | L29: Lowest of the 27, as the press release reported. Supersedes the rounded 57%.
A30: 29 | B30: CY.ECM.IND.BUY | C30: Individuals who bought online in last 12 months | D30: CY | E30: 2024 | F30: 68.16 | G30: % | H30: % of internet users | J30: ES7 | K30: 2026-09-12
A31: 30 | B31: CZ.ECM.IND.BUY | C31: Individuals who bought online in last 12 months | D31: CZ | E31: 2024 | F31: 86.21 | G31: % | H31: % of internet users | J31: ES7 | K31: 2026-09-12
A32: 31 | B32: DE.ECM.IND.BUY | C32: Individuals who bought online in last 12 months | D32: DE | E32: 2024 | F32: 82.53 | G32: % | H32: % of internet users | J32: ES7 | K32: 2026-09-12 | L32: Supersedes the rounded 83%.
A33: 32 | B33: DK.ECM.IND.BUY | C33: Individuals who bought online in last 12 months | D33: DK | E33: 2024 | F33: 90.86 | G33: % | H33: % of internet users | J33: ES7 | K33: 2026-09-12 | L33: Supersedes the rounded 91% taken from the Eurostat press release.
A34: 33 | B34: EE.ECM.IND.BUY | C34: Individuals who bought online in last 12 months | D34: EE | E34: 2024 | F34: 78.72 | G34: % | H34: % of internet users | J34: ES7 | K34: 2026-09-12
A35: 34 | B35: EL.ECM.IND.BUY | C35: Individuals who bought online in last 12 months | D35: EL | E35: 2024 | F35: 74.66 | G35: % | H35: % of internet users | J35: ES7 | K35: 2026-09-12
A36: 35 | B36: ES.ECM.IND.BUY | C36: Individuals who bought online in last 12 months | D36: ES | E36: 2024 | F36: 71.54 | G36: % | H36: % of internet users | J36: ES7 | K36: 2026-09-12
A37: 36 | B37: FI.ECM.IND.BUY | C37: Individuals who bought online in last 12 months | D37: FI | E37: 2024 | F37: 80.4 | G37: % | H37: % of internet users | J37: ES7 | K37: 2026-09-12
A38: 37 | B38: FR.ECM.IND.BUY | C38: Individuals who bought online in last 12 months | D38: FR | E38: 2024 | F38: 84.37 | G38: % | H38: % of internet users | J38: ES7 | K38: 2026-09-12
A39: 38 | B39: HR.ECM.IND.BUY | C39: Individuals who bought online in last 12 months | D39: HR | E39: 2024 | F39: 70.07 | G39: % | H39: % of internet users | J39: ES7 | K39: 2026-09-12
A40: 39 | B40: HU.ECM.IND.BUY | C40: Individuals who bought online in last 12 months | D40: HU | E40: 2024 | F40: 78.87 | G40: % | H40: % of internet users | J40: ES7 | K40: 2026-09-12 | L40: Supersedes the rounded 79%.
A41: 40 | B41: IE.ECM.IND.BUY | C41: Individuals who bought online in last 12 months | D41: IE | E41: 2024 | F41: 95.79 | G41: % | H41: % of internet users | J41: ES7 | K41: 2026-09-12 | L41: Highest in EU. Supersedes the rounded 96%.
A42: 41 | B42: IT.ECM.IND.BUY | C42: Individuals who bought online in last 12 months | D42: IT | E42: 2024 | F42: 59.6 | G42: % | H42: % of internet users | J42: ES7 | K42: 2026-09-12 | L42: Second lowest of the 27. Supersedes the rounded 60%, which tied Italy with Romania; unrounded Italy is below Romania, so they are not tied.
A43: 42 | B43: LT.ECM.IND.BUY | C43: Individuals who bought online in last 12 months | D43: LT | E43: 2024 | F43: 71.96 | G43: % | H43: % of internet users | J43: ES7 | K43: 2026-09-12 | L43: Supersedes the rounded 72%.
A44: 43 | B44: LU.ECM.IND.BUY | C44: Individuals who bought online in last 12 months | D44: LU | E44: 2024 | F44: 81.34 | G44: % | H44: % of internet users | J44: ES7 | K44: 2026-09-12
A45: 44 | B45: LV.ECM.IND.BUY | C45: Individuals who bought online in last 12 months | D45: LV | E45: 2024 | F45: 69.35 | G45: % | H45: % of internet users | J45: ES7 | K45: 2026-09-12
A46: 45 | B46: MT.ECM.IND.BUY | C46: Individuals who bought online in last 12 months | D46: MT | E46: 2024 | F46: 73.2 | G46: % | H46: % of internet users | J46: ES7 | K46: 2026-09-12
A47: 46 | B47: NL.ECM.IND.BUY | C47: Individuals who bought online in last 12 months | D47: NL | E47: 2024 | F47: 94.42 | G47: % | H47: % of internet users | J47: ES7 | K47: 2026-09-12 | L47: Supersedes the rounded 94%.
A48: 47 | B48: PL.ECM.IND.BUY | C48: Individuals who bought online in last 12 months | D48: PL | E48: 2024 | F48: 75.07 | G48: % | H48: % of internet users | J48: ES7 | K48: 2026-09-12
A49: 48 | B49: PT.ECM.IND.BUY | C49: Individuals who bought online in last 12 months | D49: PT | E49: 2024 | F49: 66.64 | G49: % | H49: % of internet users | J49: ES7 | K49: 2026-09-12
A50: 49 | B50: RO.ECM.IND.BUY | C50: Individuals who bought online in last 12 months | D50: RO | E50: 2024 | F50: 59.73 | G50: % | H50: % of internet users | J50: ES7 | K50: 2026-09-12 | L50: Supersedes the rounded 60%. See the Italy note on the tie.
A51: 50 | B51: SE.ECM.IND.BUY | C51: Individuals who bought online in last 12 months | D51: SE | E51: 2024 | F51: 89.89 | G51: % | H51: % of internet users | J51: ES7 | K51: 2026-09-12
A52: 51 | B52: SI.ECM.IND.BUY | C52: Individuals who bought online in last 12 months | D52: SI | E52: 2024 | F52: 72.39 | G52: % | H52: % of internet users | J52: ES7 | K52: 2026-09-12
A53: 52 | B53: SK.ECM.IND.BUY | C53: Individuals who bought online in last 12 months | D53: SK | E53: 2024 | F53: 85.13 | G53: % | H53: % of internet users | J53: ES7 | K53: 2026-09-12
A54: 53 | B54: EU.ECM.IND.BUY | C54: Individuals who bought online in last 12 months | D54: EU27 | E54: 2014 | F54: 59 | G54: % | H54: % of internet users | J54: ES4 | K54: 2026-09-12
A55: 54 | B55: DK.ECM.ENT.TRN | C55: E-sales as share of enterprise turnover | D55: DK | E55: 2014 | F55: 17.05 | G55: % | H55: % of total enterprise turnover | J55: ES5 | K55: 2026-09-12
A56: 55 | B56: DK.ECM.ENT.TRN | C56: E-sales as share of enterprise turnover | D56: DK | E56: 2024 | F56: 33.31 | G56: % | H56: % of total enterprise turnover | J56: ES5 | K56: 2026-09-12 | L56: 2nd in EU after Ireland.
A57: 56 | B57: EU.ECM.ENT.TRN | C57: E-sales as share of enterprise turnover | D57: EU27 | E57: 2014 | F57: 16.43 | G57: % | H57: % of total enterprise turnover | J57: ES5 | K57: 2026-09-12
A58: 57 | B58: EU.ECM.ENT.TRN | C58: E-sales as share of enterprise turnover | D58: EU27 | E58: 2024 | F58: 19.49 | G58: % | H58: % of total enterprise turnover | J58: ES5 | K58: 2026-09-12
A59: 58 | B59: IE.ECM.ENT.TRN | C59: E-sales as share of enterprise turnover | D59: IE | E59: 2024 | F59: 38.25 | G59: % | H59: % of total enterprise turnover | J59: ES5 | K59: 2026-09-12 | L59: Highest in EU.
A60: 59 | B60: BE.ECM.ENT.TRN | C60: E-sales as share of enterprise turnover | D60: BE | E60: 2024 | F60: 29.51 | G60: % | H60: % of total enterprise turnover | I60: u | J60: ES6 | K60: 2026-09-12
A61: 60 | B61: SE.ECM.ENT.TRN | C61: E-sales as share of enterprise turnover | D61: SE | E61: 2024 | F61: 26.32 | G61: % | H61: % of total enterprise turnover | I61: u | J61: ES6 | K61: 2026-09-12
A62: 61 | B62: CZ.ECM.ENT.TRN | C62: E-sales as share of enterprise turnover | D62: CZ | E62: 2024 | F62: 25.65 | G62: % | H62: % of total enterprise turnover | I62: u | J62: ES6 | K62: 2026-09-12
A63: 62 | B63: LU.ECM.ENT.TRN | C63: E-sales as share of enterprise turnover | D63: LU | E63: 2024 | F63: 23.86 | G63: % | H63: % of total enterprise turnover | I63: u | J63: ES6 | K63: 2026-09-12
A64: 63 | B64: HU.ECM.ENT.TRN | C64: E-sales as share of enterprise turnover | D64: HU | E64: 2024 | F64: 21.35 | G64: % | H64: % of total enterprise turnover | I64: u | J64: ES6 | K64: 2026-09-12
A65: 64 | B65: DE.ECM.ENT.TRN | C65: E-sales as share of enterprise turnover | D65: DE | E65: 2024 | F65: 19.05 | G65: % | H65: % of total enterprise turnover | I65: u | J65: ES6 | K65: 2026-09-12
A66: 65 | B66: AT.ECM.ENT.TRN | C66: E-sales as share of enterprise turnover | D66: AT | E66: 2024 | F66: 18.96 | G66: % | H66: % of total enterprise turnover | I66: u | J66: ES6 | K66: 2026-09-12
A67: 66 | B67: HR.ECM.ENT.TRN | C67: E-sales as share of enterprise turnover | D67: HR | E67: 2024 | F67: 18.48 | G67: % | H67: % of total enterprise turnover | I67: u | J67: ES6 | K67: 2026-09-12
A68: 67 | B68: ES.ECM.ENT.TRN | C68: E-sales as share of enterprise turnover | D68: ES | E68: 2024 | F68: 18.27 | G68: % | H68: % of total enterprise turnover | I68: u | J68: ES6 | K68: 2026-09-12
A69: 68 | B69: PL.ECM.ENT.TRN | C69: E-sales as share of enterprise turnover | D69: PL | E69: 2024 | F69: 17.66 | G69: % | H69: % of total enterprise turnover | I69: u | J69: ES6 | K69: 2026-09-12
A70: 69 | B70: SI.ECM.ENT.TRN | C70: E-sales as share of enterprise turnover | D70: SI | E70: 2024 | F70: 16.78 | G70: % | H70: % of total enterprise turnover | I70: u | J70: ES6 | K70: 2026-09-12
A71: 70 | B71: IT.ECM.ENT.TRN | C71: E-sales as share of enterprise turnover | D71: IT | E71: 2024 | F71: 15.66 | G71: % | H71: % of total enterprise turnover | I71: u | J71: ES6 | K71: 2026-09-12
... A75: 74 | B75: BG.ECM.ENT.TRN | C75: E-sales as share of enterprise turnover | D75: BG | E75: 2024 | F75: 7.63 | G75: % | H75: % of total enterprise turnover | I75: u | J75: ES6 | K75: 2026-09-12
A76: 75 | B76: DK.ECM.ENT.SHR | C76: Enterprises making e-sales | D76: DK | E76: 2024 | F76: 38.78 | G76: % | H76: % of enterprises | J76: ES5 | K76: 2026-09-12 | L76: 2nd in EU after Lithuania.
A77: 76 | B77: LT.ECM.ENT.SHR | C77: Enterprises making e-sales | D77: LT | E77: 2024 | F77: 43.03 | G77: % | H77: % of enterprises | J77: ES5 | K77: 2026-09-12 | L77: Highest in EU.
A78: 77 | B78: DK.DGP.EXMP | C78: Citizens formally exempt from Digital Post | D78: DK | E78: 2025 | F78: 5 | G78: % | H78: % of citizens aged 15+ resident in Denmark | J78: DG1 | K78: 2026-09-12 | L78: April 2025; approx. 256,000 citizens.
A79: 78 | B79: DK.DGP.EXMP | C79: Citizens formally exempt from Digital Post | D79: DK | E79: 2026 | F79: 4.7 | G79: % | H79: % of citizens aged 15+ resident in Denmark | J79: DG1 | K79: 2026-09-12 | L79: Q1 2026; 238,479 citizens. 95.2% enrolled.
A80: 79 | B80: DK.DGP.EXMP.7584 | C80: Exemption rate, age 75-84 | D80: DK | E80: 2022 | F80: 20 | G80: % | H80: % of age group | I80: e | J80: DG1 | K80: 2026-09-12 | L80: Source states 'nearly one in five'.
A81: 80 | B81: DK.DGP.EXMP.85P | C81: Exemption rate, age 85+ | D81: DK | E81: 2022 | F81: 33 | G81: % | H81: % of age group | I81: e | J81: DG1 | K81: 2026-09-12 | L81: Source states 'roughly one in three'.
A82: 81 | B82: DK.DGX.NOUSE | C82: Do not use digital public services at all | D82: DK | E82: 2026 | F82: 6.5 | G82: % | H82: % of population | J82: EC1 | K82: 2026-09-12 | L82: Agency for Digital Government estimate.
A83: 82 | B83: DK.DGX.DIFF | C83: Face difficulties using digital public services | D83: DK | E83: 2026 | F83: 16.5 | G83: % | H83: % of population | J83: EC1 | K83: 2026-09-12 | L83: Agency for Digital Government estimate.
A84: 83 | B84: DK.DGX.DISADV.LO | C84: 'Digitally disadvantaged' - lower bound | D84: DK | E84: 2025 | F84: 17 | G84: % | H84: % of adult population | I84: e | J84: DG2 | K84: 2026-09-12 | L84: Published as a 17-22% range.
A85: 84 | B85: DK.DGX.DISADV.HI | C85: 'Digitally disadvantaged' - upper bound | D85: DK | E85: 2025 | F85: 22 | G85: % | H85: % of adult population | I85: e | J85: DG2 | K85: 2026-09-12 | L85: Published as a 17-22% range.
A86: 85 | B86: DK.DGX.JUST | C86: 'Digitally disadvantaged' - Justitia estimate | D86: DK | E86: 2022 | F86: 25 | G86: % | H86: % of adult population | I86: e | J86: JU1 | K86: 2026-09-12 | L86: Report states 'up to a quarter of the adult population'.
A87: 86 | B87: DK.TRU.DPS | C87: Trust in digital public solutions | D87: DK | E87: 2024 | F87: 82 | G87: % | H87: % of population | J87: EC1 | K87: 2026-09-12
A88: 87 | B88: DK.TRU.DPS | C88: Trust in digital public solutions | D88: DK | E88: 2025 | F88: 84 | G88: % | H88: % of population | J88: EC1 | K88: 2026-09-12 | L88: Record high.
A89: 88 | B89: DK.TRU.DGP.SEC | C89: Perceived security of Digital Post | D89: DK | E89: 2017 | F89: 77 | G89: % | H89: % of population | J89: EC1 | K89: 2026-09-12
A90: 89 | B90: DK.TRU.DGP.SEC | C90: Perceived security of Digital Post | D90: DK | E90: 2025 | F90: 89 | G90: % | H90: % of population | J90: EC1 | K90: 2026-09-12
A91: 90 | B91: DK.SKL.1624 | C91: At least basic digital skills, age 16-24 | D91: DK | E91: 2025 | F91: 92.06 | G91: % | H91: % of age group | J91: EC1 | K91: 2026-09-12 | L91: EU average carried as EU.SKL.1624.
A92: 91 | B92: DK.SKL.2554 | C92: At least basic digital skills, age 25-54 | D92: DK | E92: 2025 | F92: 86.89 | G92: % | H92: % of age group | J92: EC1 | K92: 2026-09-12 | L92: EU average carried as EU.SKL.2554.
A93: 92 | B93: DK.SKL.5574 | C93: At least basic digital skills, age 55-74 | D93: DK | E93: 2025 | F93: 67.81 | G93: % | H93: % of age group | J93: EC1 | K93: 2026-09-12 | L93: EU average carried as EU.SKL.5574.
A94: 93 | B94: EU.SKL.1624 | C94: At least basic digital skills, age 16-24 | D94: EU27 | E94: 2025 | F94: 74.55 | G94: % | H94: % of age group | J94: EC1 | K94: 2026-09-12 | L94: Comparator for DK.SKL.1624.
A95: 94 | B95: EU.SKL.2554 | C95: At least basic digital skills, age 25-54 | D95: EU27 | E95: 2025 | F95: 68.57 | G95: % | H95: % of age group | J95: EC1 | K95: 2026-09-12 | L95: Comparator for DK.SKL.2554.
A96: 95 | B96: EU.SKL.5574 | C96: At least basic digital skills, age 55-74 | D96: EU27 | E96: 2025 | F96: 42.6 | G96: % | H96: % of age group | J96: EC1 | K96: 2026-09-12 | L96: Comparator for DK.SKL.5574.
A97: 96 | B97: DK.ENT.DII | C97: SMEs with at least basic digital intensity | D97: DK | E97: 2025 | F97: 92.45 | G97: % | H97: % of SMEs | J97: EC1 | K97: 2026-09-12 | L97: EU average 71.39%.
A98: 97 | B98: EU.ENT.DII | C98: SMEs with at least basic digital intensity | D98: EU27 | E98: 2025 | F98: 71.39 | G98: % | H98: % of SMEs | J98: EC1 | K98: 2026-09-12
A99: 98 | B99: DK.ENT.AI | C99: Enterprises adopting AI | D99: DK | E99: 2025 | F99: 42.03 | G99: % | H99: % of enterprises | J99: EC1 | K99: 2026-09-12 | L99: EU average 19.95%.
A100: 99 | B100: DK.ENT.AI.LRG | C100: Large enterprises adopting AI | D100: DK | E100: 2025 | F100: 74.52 | G100: % | H100: % of large enterprises (250+) | J100: EC1 | K100: 2026-09-12
A101: 100 | B101: DK.ENT.AI.SME | C101: SMEs adopting AI | D101: DK | E101: 2025 | F101: 40.99 | G101: % | H101: % of SMEs (10-249) | J101: EC1 | K101: 2026-09-12
A102: 101 | B102: DK.GOV.DPS.CIT | C102: Digital public services for citizens (score) | D102: DK | E102: 2025 | F102: 82.2 | G102: score 0-100 | H102: eGovernment Benchmark score | J102: EC1 | K102: 2026-09-12 | L102: BELOW the EU average of 84.64.
A103: 102 | B103: EU.GOV.DPS.CIT | C103: Digital public services for citizens (score) | D103: EU27 | E103: 2025 | F103: 84.64 | G103: score 0-100 | H103: eGovernment Benchmark score | J103: EC1 | K103: 2026-09-12
...

Sheet 03_SOURCES
A1: source_id | B1: authority | C1: publication | D1: dataset code | E1: URL | F1: accessed | G1: RMIT Harvard reference
A2: NB1 | B2: Danmarks Nationalbank | C2: Danskernes betalingsvaner | E2: https://www.nationalbanken.dk/en/what-we-do/safe-and-efficient-payments/payment-habits-in-denmark | F2: 2026-09-12 | G2: Danmarks Nationalbank 2025, Danskernes betalingsvaner, Danmarks Nationalbank, Copenhagen, accessed 12 September 2026, <https://www.nationalbanken.dk/en/what-we-do/safe-and-efficient-payments/payment-habits-in-denmark>.
A3: NB2 | B3: Danmarks Nationalbank | C3: [REFERENCE ONLY - supports argument in the report; no workbook value depends on it] Danskerne betaler mere digitalt - det goer offline-betalinger endnu vigtigere som beredskab (press release, 26 June 2026) | E3: https://www.nationalbanken.dk/da/viden-og-nyheder/presse/arkiv/2026/danskerne-betaler-mere-digitalt-det-goer-offline-betalinger-endnu-vigtigere-som-beredskab-26-06-2026 | F3: 2026-09-12 | G3: Danmarks Nationalbank 2026, Danskerne betaler mere digitalt - det goer offline-betalinger endnu vigtigere som beredskab, press release, 26 June, Danmarks Nationalbank, Copenhagen, accessed 12 September 2026.
A4: FD1 | B4: Finans Danmark | C4: Institutter, filialer & ansatte | E4: https://finansdanmark.dk/tal-og-data/institutter-filialer-ansatte/ | F4: 2026-09-12 | G4: Finans Danmark 2025, Institutter, filialer & ansatte, Finans Danmark, Copenhagen, accessed 12 September 2026, <https://finansdanmark.dk/tal-og-data/institutter-filialer-ansatte/>.
A5: ES1 | B5: Eurostat | C5: E-commerce statistics for individuals (Statistics Explained) | D5: isoc_ec_ib20 / isoc_ec_ibuy | E5: https://ec.europa.eu/eurostat/statistics-explained/index.php?title=E-commerce_statistics_for_individuals | F5: 2026-09-12 | G5: Eurostat 2025, E-commerce statistics for individuals, Statistics Explained, European Commission, Luxembourg, accessed 12 September 2026.
A6: ES2 | B6: Eurostat | C6: Online shopping ever more popular in 2020 (ddn-20210217-1) | D6: isoc_ec_ib20 | E6: https://ec.europa.eu/eurostat/web/products-eurostat-news/-/ddn-20210217-1 | F6: 2026-09-12 | G6: Eurostat 2021, Online shopping ever more popular in 2020, European Commission, Luxembourg, accessed 12 September 2026.
A7: ES3 | B7: Eurostat | C7: Online shopping ever more popular (ddn-20220202-1) | D7: isoc_ec_ib20 | E7: https://ec.europa.eu/eurostat/web/products-eurostat-news/-/ddn-20220202-1 | F7: 2026-09-12 | G7: Eurostat 2022, Online shopping ever more popular, European Commission, Luxembourg, accessed 12 September 2026.
A8: ES4 | B8: Eurostat | C8: E-commerce statistics for individuals, 2024 reference year (ddn-20250220-3) | D8: isoc_ec_ib20 | E8: https://ec.europa.eu/eurostat/web/products-eurostat-news/w/ddn-20250220-3 | F8: 2026-09-12 | G8: Eurostat 2025, E-commerce statistics for individuals, European Commission, Luxembourg, accessed 12 September 2026.
A9: ES5 | B9: Eurostat | C9: EU enterprises' online sales reach new heights in 2023 (ddn-20250227-2) | D9: isoc_ec_evaln2 / tin00110 | E9: https://ec.europa.eu/eurostat/web/products-eurostat-news/w/ddn-20250227-2 | F9: 2026-09-12 | G9: Eurostat 2025, EU enterprises' online sales reach new heights, European Commission, Luxembourg, accessed 12 September 2026.
A10: ES6 | B10: Eurostat | C10: Share of enterprises' turnover on e-commerce, by country (country-level values retrieved via search of the Eurostat indicator) | D10: tin00110 | E10: https://ec.europa.eu/eurostat/databrowser/view/tin00110/default/table?lang=en | F10: 2026-09-12 | G10: Eurostat 2025, Share of enterprises' turnover on e-commerce (tin00110), European Commission, Luxembourg, accessed 12 September 2026.
A11: EC1 | B11: European Commission | C11: Digital Decade 2026 country report: Denmark, SWD(2026) 155 final, Part 7/27, 17 June 2026 | D11: DESI 2026 | E11: https://digital-strategy.ec.europa.eu/en/policies/desi | F11: 2026-09-12 | G11: European Commission 2026, Digital Decade 2026 country report: Denmark, SWD(2026) 155 final, Part 7/27, European Commission, Brussels.
A12: DG1 | B12: Digitaliseringsstyrelsen (Danish Agency for Digital Government) | C12: Statistik om Digital Post | E12: https://digst.dk/tal-og-statistik/ | F12: 2026-09-12 | G12: Digitaliseringsstyrelsen 2026, Statistik om Digital Post, Agency for Digital Government, Copenhagen, accessed 12 September 2026.
A13: DG2 | B13: Digitaliseringsstyrelsen (Danish Agency for Digital Government) | C13: Hvem oplever udfordringer ved det digitale? | E13: https://digst.dk/digital-inklusion/viden-om-digital-inklusion/hvem-oplever-udfordringer-ved-det-digitale/ | F13: 2026-09-12 | G13: Digitaliseringsstyrelsen 2025, Hvem oplever udfordringer ved det digitale?, Agency for Digital Government, Copenhagen, accessed 12 September 2026.
A14: DG3 | B14: Digitaliseringsstyrelsen / Danmarks Statistik | C14: Effektmaaling af SMV:Digital, June 2025 | E14: https://digst.dk/media/yz2ouzzz/effektmaaling-af-smvdigital-2025.pdf | F14: 2026-09-12 | G14: Digitaliseringsstyrelsen 2025, Effektmaaling af SMV:Digital, prepared by Danmarks Statistik, Agency for Digital Government, Copenhagen, accessed 12 September 2026.
A15: JU1 | B15: Justitia (independent Danish legal think tank) | C15: Retssikkerhed for digitalt udsatte borgere, July 2022 | D15: Folketinget DIU Alm.del bilag 32 | E15: https://justitia-int.org/wp-content/uploads/2022/09/Rapport_Retssikkerhed-for-digitalt-udsatte-borgere-1.pdf | F15: 2026-09-12 | G15: Justitia 2022, Retssikkerhed for digitalt udsatte borgere, Justitia, Copenhagen, accessed 12 September 2026.
A16: IMR1 | B16: Institut for Menneskerettigheder (Danish Institute for Human Rights) | C16: [REFERENCE ONLY - supports argument in the report; no workbook value depends on it] Rettigheder i den digitale velfaerdsstat, December 2023 | E16: https://menneskeret.dk/sites/menneskeret.dk/files/media/document/Rettigheder%20i%20den%20digitale%20velf%C3%A6rdsstat.%20Analyse,%20Institut%20for%20Menneskerettigheder,%20december%202023.PDF | F16: 2026-09-12 | G16: Institut for Menneskerettigheder 2023, Rettigheder i den digitale velfaerdsstat, Danish Institute for Human Rights, Copenhagen, accessed 12 September 2026.
A17: RI1 | B17: Retsinformation (Danish official legal information portal) | C17: Lov om Offentlig Digital Post, LOV nr 528 af 11/06/2012 | D17: ELI: lta/2012/528 | E17: https://www.retsinformation.dk/eli/lta/2012/528 | F17: 2026-09-12 | G17: Denmark 2012, Lov om Offentlig Digital Post (LOV nr 528 af 11/06/2012), Retsinformation, Copenhagen, accessed 12 September 2026.
A18: RR1 | B18: Rigsrevisionen (Danish National Audit Office) | C18: Beretning om besparelsespotentialet ved obligatorisk Digital Post paa ca. 1 mia. kr. om aaret, January 2016 | E18: https://www.rigsrevisionen.dk/revisionssager-arkiv/2016/jan/beretning-om-besparelsespotentialet-ved-obligatorisk-digital-post-paa-ca-1-mia-kr-om-aaret | F18: 2026-09-12 | G18: Rigsrevisionen 2016, Beretning om besparelsespotentialet ved obligatorisk Digital Post paa ca. 1 mia. kr. om aaret, National Audit Office of Denmark, Copenhagen, accessed 12 September 2026.
A19: RI2 | B19: Finanstilsynet (Danish Financial Supervisory Authority) | C19: Kontantreglen - lov om betalinger section 81 | D19: Lov om betalinger, ss 81 | E19: https://www.finanstilsynet.dk/finansielle-temaer/betalingstjenester-og-e-penge/kontantreglen | F19: 2026-09-12 | G19: Finanstilsynet 2025, Kontantreglen, Danish Financial Supervisory Authority, Copenhagen, accessed 12 September 2026.
A20: DG4 | B20: Digitaliseringsstyrelsen (Danish Agency for Digital Government) | C20: Digital Post - lovgivning, and the MitID transition news archive | E20: https://digst.dk/it-loesninger/digital-post/lovgivning/ | F20: 2026-09-12 | G20: Digitaliseringsstyrelsen 2025, Digital Post - lovgivning, Agency for Digital Government, Copenhagen, accessed 12 September 2026.
A21: SMV1 | B21: SMV:Digital (Danish SME digitalisation grant scheme) | C21: Tilskudspuljer i 2026 | E21: https://smvdigital.dk/content/ydelser/tilskudspuljer-i-2026/8efa07f4-5032-47f4-b7fa-bab57412b762/ | F21: 2026-09-12 | G21: SMV:Digital 2026, Tilskudspuljer i 2026, SMV:Digital, Copenhagen, accessed 12 September 2026.
A22: DST2 | B22: Danmarks Statistik | C22: Befolkningstal (population figures) | D22: StatBank FOLK1A | E22: https://www.dst.dk/da/Statistik/emner/borgere/befolkning/befolkningstal | F22: 2026-09-12 | G22: Danmarks Statistik 2026, Befolkningstal, Statistics Denmark, Copenhagen, accessed 12 September 2026.
A23: ES7 | B23: Eurostat | C23: Internet purchases by individuals (2020 onwards) - custom extraction, all individuals, last online purchase in the 12 months, percentage of individuals who used internet within the last year, 2024 | D23: isoc_ec_ib20 | E23: https://ec.europa.eu/eurostat/databrowser/view/isoc_ec_ib20/default/table?lang=en | F23: 2026-09-12 | G23: Eurostat 2026, Internet purchases by individuals (2020 onwards), dataset isoc_ec_ib20, Statistical Office of the European Union, Luxembourg, data last updated 17 April 2026, accessed 12 September 2026, <https://ec.europa.eu/eurostat/databrowser/view/isoc_ec_ib20/default/table?lang=en>.
A24: DST1 | B24: Danmarks Statistik | C24: Detailomsaetningsindeks (retail trade turnover index) | D24: StatBank; base year rebased 2015 -> 2021 | E24: https://www.dst.dk/da/Statistik/dokumentation/statistikdokumentation/detailomsaetningsindeks | F24: 2026-09-12 | G24: Danmarks Statistik 2025, Detailomsaetningsindeks, Statistics Denmark, Copenhagen, accessed 12 September 2026.

Sheet 04_DEFINITIONS
A1: series_code | B1: what it measures | C1: what it excludes / watch for
A2: PREFIXES: definitions below are written against the DK.* codes. The same definition applies to the identical indicator for any other geography - EU.*, and the member-state codes AT.* through SE.* used in F5_EU27 and F6_ADOPT_BENEFIT. Only the geography changes; the measure and its denominator do not.
A3: DK.PAY.CASH.POS | B3: Cash as a share of the NUMBER of payments made at physical points of sale. | C3: Not a share of value. Excludes e-commerce entirely.
A4: DK.PAY.CRD.PHYS | B4: Physical payment cards as a share of the number of in-store payments. | C4: Falls partly because wallets replace the physical card, not because card payment declines.
A5: DK.PAY.WLT.SHR | B5: Card-based mobile wallets as a share of the number of in-store payments. | C5: Wallet payments are card payments. Do not add to the card share.
A6: DK.PAY.WLT.OWN | B6: Share of CITIZENS with a wallet solution on their phone. | C6: Different denominator from the payment-share series. Memo only - deliberately excluded from Figure 2.
A7: DK.FIN.BRCH | B7: Number of retail bank branches operated by Danish credit institutions. | C7: Consolidation and digitalisation both reduce this. The series alone cannot separate the two causes.
A8: DK.ECM.IND.BUY | B8: Individuals who purchased goods or services online in the last 12 months. | C8: DENOMINATOR BREAK at 2020: % of individuals before, % of internet users after. Never plot 2019 with later years.
A9: DK.ECM.ENT.TRN | B9: E-commerce sales as a share of total enterprise turnover. | C9: Measures INTENSITY of online selling, not how many firms sell online. Pair with DK.ECM.ENT.SHR.
A10: DK.ECM.ENT.SHR | B10: Share of enterprises making any e-sales. | C10: Measures BREADTH of adoption. Flat breadth with rising intensity means incumbents deepening, not new entrants.
A11: DK.DGP.EXMP | B11: Citizens formally exempt from mandatory Digital Post under the statutory exemption regime. | C11: An administrative status, not a measure of capability. A citizen may struggle without being exempt.
A12: DK.DGX.DIFF | B12: Population estimated to face difficulties using digital public services. | C12: A capability estimate, not an administrative count. Much larger than the exemption rate - that gap is the analytical point.
A13: DK.DGX.JUST | B13: Justitia's estimate of the digitally disadvantaged adult population. | C13: Think-tank estimate, broadest definition of the five. Cite as an upper bound, not as an official statistic.
A14: DK.GOV.DPS.CIT | B14: eGovernment Benchmark composite score for citizen-facing digital public services. | C14: A composite index, not a usage rate. Denmark scores BELOW the EU average despite near-universal mandated use.
... A31: DK.SME.SMVD.PROJ, DK.SME.SMVD.INV, DK.SME.SMVD.NOINV | B31: SMV:Digital programme: projects supported, and participants who did or did not invest further. | C31: Self-reported by participants, with no control group. Cannot support a causal claim about the programme - see the withdrawn claim in 07_LIMITATIONS and 08_AI_LOG.

Sheet 05_CALC
A1: Derived quantities
A2: Every cell below is a live formula over 02_MASTER. No pasted numbers.
A4: quantity | B4: formula result | C4: unit | D4: how it is built
A5: Bank branches, 2004 | B5: =IF(COUNTIFS('02_MASTER'!$B:$B,"DK.FIN.BRCH",'02_MASTER'!$E:$E,2004)=0,"",SUMIFS('02_MASTER'!$F:$F,'02_MASTER'!$B:$B,"DK.FIN.BRCH",'02_MASTER'!$E:$E,2004)) | C5: count | D5: Direct lookup from 02_MASTER.
A6: Bank branches, 2024 | B6: =IF(COUNTIFS('02_MASTER'!$B:$B,"DK.FIN.BRCH",'02_MASTER'!$E:$E,2024)=0,"",SUMIFS('02_MASTER'!$F:$F,'02_MASTER'!$B:$B,"DK.FIN.BRCH",'02_MASTER'!$E:$E,2024)) | C6: count | D6: Direct lookup from 02_MASTER.
A7: Branch network change, 2004-2024 | B7: =(IF(COUNTIFS('02_MASTER'!$B:$B,"DK.FIN.BRCH",'02_MASTER'!$E:$E,2024)=0,"",SUMIFS('02_MASTER'!$F:$F,'02_MASTER'!$B:$B,"DK.FIN.BRCH",'02_MASTER'!$E:$E,2024))/IF(COUNTIFS('02_MASTER'!$B:$B,"DK.FIN.BRCH",'02_MASTER'!$E:$E,2004)=0,"",SUMIFS('02_MASTER'!$F:$F,'02_MASTER'!$B:$B,"DK.FIN.BRCH",'02_MASTER'!$E:$E,2004)))-1 | C7: % | D7: Headline structural change for Figure 1.
A8: Cash share change, 2017-2025 | B8: =IF(COUNTIFS('02_MASTER'!$B:$B,"DK.PAY.CASH.POS",'02_MASTER'!$E:$E,2025)=0,"",SUMIFS('02_MASTER'!$F:$F,'02_MASTER'!$B:$B,"DK.PAY.CASH.POS",'02_MASTER'!$E:$E,2025))-IF(COUNTIFS('02_MASTER'!$B:$B,"DK.PAY.CASH.POS",'02_MASTER'!$E:$E,2017)=0,"",SUMIFS('02_MASTER'!$F:$F,'02_MASTER'!$B:$B,"DK.PAY.CASH.POS",'02_MASTER'!$E:$E,2017)) | C8: pp | D8: Percentage-point change, not a growth rate - both terms are shares.
A9: Cash share, proportional decline 2017-2025 | B9: =(IF(COUNTIFS('02_MASTER'!$B:$B,"DK.PAY.CASH.POS",'02_MASTER'!$E:$E,2025)=0,"",SUMIFS('02_MASTER'!$F:$F,'02_MASTER'!$B:$B,"DK.PAY.CASH.POS",'02_MASTER'!$E:$E,2025))/IF(COUNTIFS('02_MASTER'!$B:$B,"DK.PAY.CASH.POS",'02_MASTER'!$E:$E,2017)=0,"",SUMIFS('02_MASTER'!$F:$F,'02_MASTER'!$B:$B,"DK.PAY.CASH.POS",'02_MASTER'!$E:$E,2017)))-1 | C9: % | D9: Cash fell to roughly a third of its 2017 share.
A10: DK e-sales turnover share, change 2014-2024 | B10: =(IF(COUNTIFS('02_MASTER'!$B:$B,"DK.ECM.ENT.TRN",'02_MASTER'!$E:$E,2024)=0,"",SUMIFS('02_MASTER'!$F:$F,'02_MASTER'!$B:$B,"DK.ECM.ENT.TRN",'02_MASTER'!$E:$E,2024))/IF(COUNTIFS('02_MASTER'!$B:$B,"DK.ECM.ENT.TRN",'02_MASTER'!$E:$E,2014)=0,"",SUMIFS('02_MASTER'!$F:$F,'02_MASTER'!$B:$B,"DK.ECM.ENT.TRN",'02_MASTER'!$E:$E,2014)))-1 | C10: % | D10: Tests the 'enterprise plateau' claim. Intensity nearly doubled.
A11: EU e-sales turnover share, change 2014-2024 | B11: =(IF(COUNTIFS('02_MASTER'!$B:$B,"EU.ECM.ENT.TRN",'02_MASTER'!$E:$E,2024)=0,"",SUMIFS('02_MASTER'!$F:$F,'02_MASTER'!$B:$B,"EU.ECM.ENT.TRN",'02_MASTER'!$E:$E,2024))/IF(COUNTIFS('02_MASTER'!$B:$B,"EU.ECM.ENT.TRN",'02_MASTER'!$E:$E,2014)=0,"",SUMIFS('02_MASTER'!$F:$F,'02_MASTER'!$B:$B,"EU.ECM.ENT.TRN",'02_MASTER'!$E:$E,2014)))-1 | C11: % | D11: Comparator for the line above.
A12: DK lead over EU on e-sales turnover, 2024 | B12: =IF(COUNTIFS('02_MASTER'!$B:$B,"DK.ECM.ENT.TRN",'02_MASTER'!$E:$E,2024)=0,"",SUMIFS('02_MASTER'!$F:$F,'02_MASTER'!$B:$B,"DK.ECM.ENT.TRN",'02_MASTER'!$E:$E,2024))-IF(COUNTIFS('02_MASTER'!$B:$B,"EU.ECM.ENT.TRN",'02_MASTER'!$E:$E,2024)=0,"",SUMIFS('02_MASTER'!$F:$F,'02_MASTER'!$B:$B,"EU.ECM.ENT.TRN",'02_MASTER'!$E:$E,2024)) | C12: pp | D12: Denmark's margin over the EU average.
A13: Exclusion ratio: difficulty vs formal exemption | B13: =IF(COUNTIFS('02_MASTER'!$B:$B,"DK.DGX.DIFF",'02_MASTER'!$E:$E,2026)=0,"",SUMIFS('02_MASTER'!$F:$F,'02_MASTER'!$B:$B,"DK.DGX.DIFF",'02_MASTER'!$E:$E,2026))/IF(COUNTIFS('02_MASTER'!$B:$B,"DK.DGP.EXMP",'02_MASTER'!$E:$E,2026)=0,"",SUMIFS('02_MASTER'!$F:$F,'02_MASTER'!$B:$B,"DK.DGP.EXMP",'02_MASTER'!$E:$E,2026)) | C13: ratio | D13: How many times larger the capability measure is than the administrative one. The core Q4 statistic.
A14: Citizens struggling but NOT exempt | B14: =IF(COUNTIFS('02_MASTER'!$B:$B,"DK.DGX.DIFF",'02_MASTER'!$E:$E,2026)=0,"",SUMIFS('02_MASTER'!$F:$F,'02_MASTER'!$B:$B,"DK.DGX.DIFF",'02_MASTER'!$E:$E,2026))-IF(COUNTIFS('02_MASTER'!$B:$B,"DK.DGP.EXMP",'02_MASTER'!$E:$E,2026)=0,"",SUMIFS('02_MASTER'!$F:$F,'02_MASTER'!$B:$B,"DK.DGP.EXMP",'02_MASTER'!$E:$E,2026)) | C14: pp | D14: Population facing difficulty without statutory relief.
A15: Digital skills gap, 16-24 vs 55-74 | B15: =IF(COUNTIFS('02_MASTER'!$B:$B,"DK.SKL.1624",'02_MASTER'!$E:$E,2025)=0,"",SUMIFS('02_MASTER'!$F:$F,'02_MASTER'!$B:$B,"DK.SKL.1624",'02_MASTER'!$E:$E,2025))-IF(COUNTIFS('02_MASTER'!$B:$B,"DK.SKL.5574",'02_MASTER'!$E:$E,2025)=0,"",SUMIFS('02_MASTER'!$F:$F,'02_MASTER'!$B:$B,"DK.SKL.5574",'02_MASTER'!$E:$E,2025)) | C15: pp | D15: Generational gradient in basic digital skills.
A16: AI adoption gap, large firms vs SMEs | B16: =IF(COUNTIFS('02_MASTER'!$B:$B,"DK.ENT.AI.LRG",'02_MASTER'!$E:$E,2025)=0,"",SUMIFS('02_MASTER'!$F:$F,'02_MASTER'!$B:$B,"DK.ENT.AI.LRG",'02_MASTER'!$E:$E,2025))-IF(COUNTIFS('02_MASTER'!$B:$B,"DK.ENT.AI.SME",'02_MASTER'!$E:$E,2025)=0,"",SUMIFS('02_MASTER'!$F:$F,'02_MASTER'!$B:$B,"DK.ENT.AI.SME",'02_MASTER'!$E:$E,2025)) | C16: pp | D16: Depth-of-adoption gap behind the 'breadth without depth' finding.
A17: DK shortfall vs EU, citizen digital public services | B17: =IF(COUNTIFS('02_MASTER'!$B:$B,"DK.GOV.DPS.CIT",'02_MASTER'!$E:$E,2025)=0,"",SUMIFS('02_MASTER'!$F:$F,'02_MASTER'!$B:$B,"DK.GOV.DPS.CIT",'02_MASTER'!$E:$E,2025))-IF(COUNTIFS('02_MASTER'!$B:$B,"EU.GOV.DPS.CIT",'02_MASTER'!$E:$E,2025)=0,"",SUMIFS('02_MASTER'!$F:$F,'02_MASTER'!$B:$B,"EU.GOV.DPS.CIT",'02_MASTER'!$E:$E,2025)) | C17: points | D17: Negative: Denmark scores below the EU average.
A18: DK shortfall vs EU, ICT waste recycling | B18: =IF(COUNTIFS('02_MASTER'!$B:$B,"DK.ENV.WEEE",'02_MASTER'!$E:$E,2023)=0,"",SUMIFS('02_MASTER'!$F:$F,'02_MASTER'!$B:$B,"DK.ENV.WEEE",'02_MASTER'!$E:$E,2023))-IF(COUNTIFS('02_MASTER'!$B:$B,"EU.ENV.WEEE",'02_MASTER'!$E:$E,2023)=0,"",SUMIFS('02_MASTER'!$F:$F,'02_MASTER'!$B:$B,"EU.ENV.WEEE",'02_MASTER'!$E:$E,2023)) | C18: pp | D18: Negative and large - candidate SDG evidence.
A19: Trust in digital public solutions, change 2024-2025 | B19: =IF(COUNTIFS('02_MASTER'!$B:$B,"DK.TRU.DPS",'02_MASTER'!$E:$E,2025)=0,"",SUMIFS('02_MASTER'!$F:$F,'02_MASTER'!$B:$B,"DK.TRU.DPS",'02_MASTER'!$E:$E,2025))-IF(COUNTIFS('02_MASTER'!$B:$B,"DK.TRU.DPS",'02_MASTER'!$E:$E,2024)=0,"",SUMIFS('02_MASTER'!$F:$F,'02_MASTER'!$B:$B,"DK.TRU.DPS",'02_MASTER'!$E:$E,2024)) | C19: pp | D19: Trust rising while the mandate is in force.
A20: Perceived security of Digital Post, change 2017-2025 | B20: =IF(COUNTIFS('02_MASTER'!$B:$B,"DK.TRU.DGP.SEC",'02_MASTER'!$E:$E,2025)=0,"",SUMIFS('02_MASTER'!$F:$F,'02_MASTER'!$B:$B,"DK.TRU.DGP.SEC",'02_MASTER'!$E:$E,2025))-IF(COUNTIFS('02_MASTER'!$B:$B,"DK.TRU.DGP.SEC",'02_MASTER'!$E:$E,2017)=0,"",SUMIFS('02_MASTER'!$F:$F,'02_MASTER'!$B:$B,"DK.TRU.DGP.SEC",'02_MASTER'!$E:$E,2017)) | C20: pp | D20: Trust in the mandated system over the mandate period (CLO4).
A21: Digital Post: projected annual saving | B21: =IF(COUNTIFS('02_MASTER'!$B:$B,"DK.GOV.DGP.SAVE.PLAN",'02_MASTER'!$E:$E,2016)=0,"",SUMIFS('02_MASTER'!$F:$F,'02_MASTER'!$B:$B,"DK.GOV.DGP.SAVE.PLAN",'02_MASTER'!$E:$E,2016)) | C21: mDKK/yr | D21: Ministry of Finance business case for the mandate (RR1).
A22: Digital Post: saving verifiable by audit | B22: =IF(COUNTIFS('02_MASTER'!$B:$B,"DK.GOV.DGP.SAVE.VERIF",'02_MASTER'!$E:$E,2016)=0,"",SUMIFS('02_MASTER'!$F:$F,'02_MASTER'!$B:$B,"DK.GOV.DGP.SAVE.VERIF",'02_MASTER'!$E:$E,2016)) | C22: mDKK/yr | D22: Postage, paper and envelopes only (RR1).
A23: Digital Post: unverified share of the business case | B23: =1-(IF(COUNTIFS('02_MASTER'!$B:$B,"DK.GOV.DGP.SAVE.VERIF",'02_MASTER'!$E:$E,2016)=0,"",SUMIFS('02_MASTER'!$F:$F,'02_MASTER'!$B:$B,"DK.GOV.DGP.SAVE.VERIF",'02_MASTER'!$E:$E,2016))/IF(COUNTIFS('02_MASTER'!$B:$B,"DK.GOV.DGP.SAVE.PLAN",'02_MASTER'!$E:$E,2016)=0,"",SUMIFS('02_MASTER'!$F:$F,'02_MASTER'!$B:$B,"DK.GOV.DGP.SAVE.PLAN",'02_MASTER'!$E:$E,2016))) | C23: % | D23: Over half the projected saving - the wage and overhead component - was never substantiated. The cross-government study intended to test it was abandoned. The strongest cost-side finding in this workbook.
A24: Digital Post: cost per formally exempt citizen, if the shortfall is real | B24: =((IF(COUNTIFS('02_MASTER'!$B:$B,"DK.GOV.DGP.SAVE.PLAN",'02_MASTER'!$E:$E,2016)=0,"",SUMIFS('02_MASTER'!$F:$F,'02_MASTER'!$B:$B,"DK.GOV.DGP.SAVE.PLAN",'02_MASTER'!$E:$E,2016))-IF(COUNTIFS('02_MASTER'!$B:$B,"DK.GOV.DGP.SAVE.VERIF",'02_MASTER'!$E:$E,2016)=0,"",SUMIFS('02_MASTER'!$F:$F,'02_MASTER'!$B:$B,"DK.GOV.DGP.SAVE.VERIF",'02_MASTER'!$E:$E,2016)))*1000000)/IF(COUNTIFS('02_MASTER'!$B:$B,"DK.DGP.EXMP.N",'02_MASTER'!$E:$E,2026)=0,"",SUMIFS('02_MASTER'!$F:$F,'02_MASTER'!$B:$B,"DK.DGP.EXMP.N",'02_MASTER'!$E:$E,2026)) | C24: DKK | D24: ILLUSTRATIVE ONLY, and not a real unit cost: it divides an unverified saving shortfall by an unrelated headcount. Included because the comparison of magnitudes is informative; it must not be quoted as a cost per person.
A25: Resident population, 1 January 2026 | B25: =IF(COUNTIFS('02_MASTER'!$B:$B,"DK.POP.TOT",'02_MASTER'!$E:$E,2026)=0,"",SUMIFS('02_MASTER'!$F:$F,'02_MASTER'!$B:$B,"DK.POP.TOT",'02_MASTER'!$E:$E,2026)) | C25: count | D25: Direct lookup. The only population level in the workbook (DST2).
A26: Citizens formally exempt from Digital Post, Q1 2026 | B26: =IF(COUNTIFS('02_MASTER'!$B:$B,"DK.DGP.EXMP.N",'02_MASTER'!$E:$E,2026)=0,"",SUMIFS('02_MASTER'!$F:$F,'02_MASTER'!$B:$B,"DK.DGP.EXMP.N",'02_MASTER'!$E:$E,2026)) | C26: count | D26: Headcount behind the 4.7% rate (DG1).
A27: Change in exempt headcount, 2025 to 2026 | B27: =IF(COUNTIFS('02_MASTER'!$B:$B,"DK.DGP.EXMP.N",'02_MASTER'!$E:$E,2026)=0,"",SUMIFS('02_MASTER'!$F:$F,'02_MASTER'!$B:$B,"DK.DGP.EXMP.N",'02_MASTER'!$E:$E,2026))-IF(COUNTIFS('02_MASTER'!$B:$B,"DK.DGP.EXMP.N",'02_MASTER'!$E:$E,2025)=0,"",SUMIFS('02_MASTER'!$F:$F,'02_MASTER'!$B:$B,"DK.DGP.EXMP.N",'02_MASTER'!$E:$E,2025)) | C27: count | D27: Falling. Note the 2025 figure is an 'approximately' value, so this difference is not precise.

Sheet F1_BRANCHES
A1: Figure 1 - Denmark's bank branch network, 2004-2024
A2: Series DK.FIN.BRCH. Values are formula lookups from 02_MASTER.
D3: Bank branches in Denmark, 2004-2024
A4: year | B4: bank branches | D4: Count of retail branches. Uneven year spacing, numeric X axis.
A5: 2004 | B5: =IF(COUNTIFS('02_MASTER'!$B:$B,"DK.FIN.BRCH",'02_MASTER'!$E:$E,2004)=0,"",SUMIFS('02_MASTER'!$F:$F,'02_MASTER'!$B:$B,"DK.FIN.BRCH",'02_MASTER'!$E:$E,2004))
A6: 2006 | B6: =IF(COUNTIFS('02_MASTER'!$B:$B,"DK.FIN.BRCH",'02_MASTER'!$E:$E,2006)=0,"",SUMIFS('02_MASTER'!$F:$F,'02_MASTER'!$B:$B,"DK.FIN.BRCH",'02_MASTER'!$E:$E,2006))
A7: 2010 | B7: =IF(COUNTIFS('02_MASTER'!$B:$B,"DK.FIN.BRCH",'02_MASTER'!$E:$E,2010)=0,"",SUMIFS('02_MASTER'!$F:$F,'02_MASTER'!$B:$B,"DK.FIN.BRCH",'02_MASTER'!$E:$E,2010))
A8: 2016 | B8: =IF(COUNTIFS('02_MASTER'!$B:$B,"DK.FIN.BRCH",'02_MASTER'!$E:$E,2016)=0,"",SUMIFS('02_MASTER'!$F:$F,'02_MASTER'!$B:$B,"DK.FIN.BRCH",'02_MASTER'!$E:$E,2016))
A9: 2021 | B9: =IF(COUNTIFS('02_MASTER'!$B:$B,"DK.FIN.BRCH",'02_MASTER'!$E:$E,2021)=0,"",SUMIFS('02_MASTER'!$F:$F,'02_MASTER'!$B:$B,"DK.FIN.BRCH",'02_MASTER'!$E:$E,2021))
A10: 2024 | B10: =IF(COUNTIFS('02_MASTER'!$B:$B,"DK.FIN.BRCH",'02_MASTER'!$E:$E,2024)=0,"",SUMIFS('02_MASTER'!$F:$F,'02_MASTER'!$B:$B,"DK.FIN.BRCH",'02_MASTER'!$E:$E,2024))
A12: Source: Finans Danmark, Institutter, filialer & ansatte (FD1). Note: years are unevenly spaced, so the chart uses a numeric X axis - a category axis would imply a constant rate of decline that the data does not show.

Sheet F2_PAYMENTS
A1: Figure 2 - Cash displacement in Danish physical retail
A2: Denominator throughout: share of the NUMBER of in-store payments.
A4: Panel A - Cash share of in-store payments | D4: Cash share of in-store payments, 2017-2025
A5: year | B5: cash (%) | D5: % of the number of payments made in physical retail.
A6: 2017 | B6: =IF(COUNTIFS('02_MASTER'!$B:$B,"DK.PAY.CASH.POS",'02_MASTER'!$E:$E,2017)=0,"",SUMIFS('02_MASTER'!$F:$F,'02_MASTER'!$B:$B,"DK.PAY.CASH.POS",'02_MASTER'!$E:$E,2017))
A7: 2023 | B7: =IF(COUNTIFS('02_MASTER'!$B:$B,"DK.PAY.CASH.POS",'02_MASTER'!$E:$E,2023)=0,"",SUMIFS('02_MASTER'!$F:$F,'02_MASTER'!$B:$B,"DK.PAY.CASH.POS",'02_MASTER'!$E:$E,2023))
A8: 2025 | B8: =IF(COUNTIFS('02_MASTER'!$B:$B,"DK.PAY.CASH.POS",'02_MASTER'!$E:$E,2025)=0,"",SUMIFS('02_MASTER'!$F:$F,'02_MASTER'!$B:$B,"DK.PAY.CASH.POS",'02_MASTER'!$E:$E,2025))
A10: Panel B - Composition of in-store payments, 2025 | D10: Composition of in-store payments, 2025
A11: instrument | B11: share of payments (%) | D11: Sums to 95%; the residual is other digital instruments.
A12: Physical payment card | B12: =IF(COUNTIFS('02_MASTER'!$B:$B,"DK.PAY.CRD.PHYS",'02_MASTER'!$E:$E,2025)=0,"",SUMIFS('02_MASTER'!$F:$F,'02_MASTER'!$B:$B,"DK.PAY.CRD.PHYS",'02_MASTER'!$E:$E,2025))
A13: Mobile wallet (card-based) | B13: =IF(COUNTIFS('02_MASTER'!$B:$B,"DK.PAY.WLT.SHR",'02_MASTER'!$E:$E,2025)=0,"",SUMIFS('02_MASTER'!$F:$F,'02_MASTER'!$B:$B,"DK.PAY.WLT.SHR",'02_MASTER'!$E:$E,2025))
A14: Cash | B14: =IF(COUNTIFS('02_MASTER'!$B:$B,"DK.PAY.CASH.POS",'02_MASTER'!$E:$E,2025)=0,"",SUMIFS('02_MASTER'!$F:$F,'02_MASTER'!$B:$B,"DK.PAY.CASH.POS",'02_MASTER'!$E:$E,2025))
A16: MEMO - different denominator, not charted above
A17: year | B17: citizens holding a mobile wallet (%)
A18: 2019 | B18: =IF(COUNTIFS('02_MASTER'!$B:$B,"DK.PAY.WLT.OWN",'02_MASTER'!$E:$E,2019)=0,"",SUMIFS('02_MASTER'!$F:$F,'02_MASTER'!$B:$B,"DK.PAY.WLT.OWN",'02_MASTER'!$E:$E,2019))
A19: 2023 | B19: =IF(COUNTIFS('02_MASTER'!$B:$B,"DK.PAY.WLT.OWN",'02_MASTER'!$E:$E,2023)=0,"",SUMIFS('02_MASTER'!$F:$F,'02_MASTER'!$B:$B,"DK.PAY.WLT.OWN",'02_MASTER'!$E:$E,2023))
A20: 2025 | B20: =IF(COUNTIFS('02_MASTER'!$B:$B,"DK.PAY.WLT.OWN",'02_MASTER'!$E:$E,2025)=0,"",SUMIFS('02_MASTER'!$F:$F,'02_MASTER'!$B:$B,"DK.PAY.WLT.OWN",'02_MASTER'!$E:$E,2025))
A23: POLICY EVENTS ON THIS SERIES
A24: date | B24: precision | C24: instrument | D24: citation | E24: source
A25: 2022-07-01 | B25: day | C25: Kontantreglen amended | D25: Lov om betalinger, ss 81 | E25: RI2
A27: Source: Danmarks Nationalbank, Danskernes betalingsvaner (NB1). Panel B sums to 95%, not 100%: the residual is other digital instruments (chiefly account transfers and non-card mobile payments). Wallet payments ARE card payments settled through a phone, so the wallet and physical-card rows must not be added to produce a 'card' total. The memo series is excluded from both panels because its denominator is % of citizens, not % of payments. Physical card and wallet shares are observed in 2025 only, so no time series is drawn for them - a two-point line through an unobserved middle would assert a path the data does not contain.

Sheet F3_ESALES
A1: Figure 3 - E-sales as a share of enterprise turnover, DK vs EU
A2: Tests the 'enterprise plateau' claim: intensity nearly doubled.
E3: E-sales as % of enterprise turnover, DK vs EU-27
A4: year | B4: Denmark | C4: EU-27 | E4: Denmark in blue; the EU average in grey.
A5: 2014 | B5: =IF(COUNTIFS('02_MASTER'!$B:$B,"DK.ECM.ENT.TRN",'02_MASTER'!$E:$E,2014)=0,"",SUMIFS('02_MASTER'!$F:$F,'02_MASTER'!$B:$B,"DK.ECM.ENT.TRN",'02_MASTER'!$E:$E,2014)) | C5: =IF(COUNTIFS('02_MASTER'!$B:$B,"EU.ECM.ENT.TRN",'02_MASTER'!$E:$E,2014)=0,"",SUMIFS('02_MASTER'!$F:$F,'02_MASTER'!$B:$B,"EU.ECM.ENT.TRN",'02_MASTER'!$E:$E,2014))
A6: 2024 | B6: =IF(COUNTIFS('02_MASTER'!$B:$B,"DK.ECM.ENT.TRN",'02_MASTER'!$E:$E,2024)=0,"",SUMIFS('02_MASTER'!$F:$F,'02_MASTER'!$B:$B,"DK.ECM.ENT.TRN",'02_MASTER'!$E:$E,2024)) | C6: =IF(COUNTIFS('02_MASTER'!$B:$B,"EU.ECM.ENT.TRN",'02_MASTER'!$E:$E,2024)=0,"",SUMIFS('02_MASTER'!$F:$F,'02_MASTER'!$B:$B,"EU.ECM.ENT.TRN",'02_MASTER'!$E:$E,2024))
A9: CONTEXT - breadth vs intensity, 2024
A10: measure | B10: Denmark | C10: EU / leader
A11: Enterprises making e-sales (%) | B11: =IF(COUNTIFS('02_MASTER'!$B:$B,"DK.ECM.ENT.SHR",'02_MASTER'!$E:$E,2024)=0,"",SUMIFS('02_MASTER'!$F:$F,'02_MASTER'!$B:$B,"DK.ECM.ENT.SHR",'02_MASTER'!$E:$E,2024)) | C11: Lithuania 43.03 (highest)
A12: E-sales share of turnover (%) | B12: =IF(COUNTIFS('02_MASTER'!$B:$B,"DK.ECM.ENT.TRN",'02_MASTER'!$E:$E,2024)=0,"",SUMIFS('02_MASTER'!$F:$F,'02_MASTER'!$B:$B,"DK.ECM.ENT.TRN",'02_MASTER'!$E:$E,2024)) | C12: Ireland 38.25 (highest)
A13: EU average, e-sales share of turnover (%) | B13: =IF(COUNTIFS('02_MASTER'!$B:$B,"EU.ECM.ENT.TRN",'02_MASTER'!$E:$E,2024)=0,"",SUMIFS('02_MASTER'!$F:$F,'02_MASTER'!$B:$B,"EU.ECM.ENT.TRN",'02_MASTER'!$E:$E,2024))
A16: POLICY EVENTS ON THIS SERIES
A17: date | B17: precision | C17: instrument | D17: citation | E17: source
A18: 2013-01-01 | B18: year | C18: Digital Post becomes mandatory for businesses | D18: Lov om Offentlig Digital Post | E18: DG4
A20: Source: Eurostat (ES5). Reading: Denmark's e-sales share of turnover rose from 17.05% to 33.31% while the EU average moved from 16.43% to 19.49%. Breadth of adoption is flat at roughly 38% of enterprises; intensity nearly doubled. The growth came from incumbents selling more online, not from new firms entering.

Sheet F4_EXCLUSION
A1: Figure 4 - Five measures of digital exclusion in Denmark
A2: Same phenomenon, five definitions. The spread is the finding.
F3: Measures of digital exclusion, Denmark
A4: measure | B4: % | C4: definition basis | D4: source | F4: Five definitions of the same phenomenon; they are nested, not contradictory.
A5: Formally exempt from Digital Post (Q1 2026) | B5: =IF(COUNTIFS('02_MASTER'!$B:$B,"DK.DGP.EXMP",'02_MASTER'!$E:$E,2026)=0,"",SUMIFS('02_MASTER'!$F:$F,'02_MASTER'!$B:$B,"DK.DGP.EXMP",'02_MASTER'!$E:$E,2026)) | C5: administrative status | D5: DG1
A6: Do not use digital public services at all | B6: =IF(COUNTIFS('02_MASTER'!$B:$B,"DK.DGX.NOUSE",'02_MASTER'!$E:$E,2026)=0,"",SUMIFS('02_MASTER'!$F:$F,'02_MASTER'!$B:$B,"DK.DGX.NOUSE",'02_MASTER'!$E:$E,2026)) | C6: self-reported non-use | D6: EC1
A7: Face difficulties using digital public services | B7: =IF(COUNTIFS('02_MASTER'!$B:$B,"DK.DGX.DIFF",'02_MASTER'!$E:$E,2026)=0,"",SUMIFS('02_MASTER'!$F:$F,'02_MASTER'!$B:$B,"DK.DGX.DIFF",'02_MASTER'!$E:$E,2026)) | C7: capability estimate | D7: EC1
A8: 'Digitally disadvantaged' - lower bound | B8: =IF(COUNTIFS('02_MASTER'!$B:$B,"DK.DGX.DISADV.LO",'02_MASTER'!$E:$E,2025)=0,"",SUMIFS('02_MASTER'!$F:$F,'02_MASTER'!$B:$B,"DK.DGX.DISADV.LO",'02_MASTER'!$E:$E,2025)) | C8: capability estimate (range) | D8: DG2
A9: 'Digitally disadvantaged' - upper bound | B9: =IF(COUNTIFS('02_MASTER'!$B:$B,"DK.DGX.DISADV.HI",'02_MASTER'!$E:$E,2025)=0,"",SUMIFS('02_MASTER'!$F:$F,'02_MASTER'!$B:$B,"DK.DGX.DISADV.HI",'02_MASTER'!$E:$E,2025)) | C9: capability estimate (range) | D9: DG2
A10: 'Digitally disadvantaged' - Justitia | B10: =IF(COUNTIFS('02_MASTER'!$B:$B,"DK.DGX.JUST",'02_MASTER'!$E:$E,2022)=0,"",SUMIFS('02_MASTER'!$F:$F,'02_MASTER'!$B:$B,"DK.DGX.JUST",'02_MASTER'!$E:$E,2022)) | C10: broadest definition | D10: JU1
A12: AGE GRADIENT IN FORMAL EXEMPTION (2022)
A13: age group | B13: exempt (%)
A14: Age 75-84 | B14: =IF(COUNTIFS('02_MASTER'!$B:$B,"DK.DGP.EXMP.7584",'02_MASTER'!$E:$E,2022)=0,"",SUMIFS('02_MASTER'!$F:$F,'02_MASTER'!$B:$B,"DK.DGP.EXMP.7584",'02_MASTER'!$E:$E,2022))
A15: Age 85+ | B15: =IF(COUNTIFS('02_MASTER'!$B:$B,"DK.DGP.EXMP.85P",'02_MASTER'!$E:$E,2022)=0,"",SUMIFS('02_MASTER'!$F:$F,'02_MASTER'!$B:$B,"DK.DGP.EXMP.85P",'02_MASTER'!$E:$E,2022))
A17: HEADCOUNTS, NOT SHARES
A18: quantity | B18: persons | C18: basis
A19: Citizens formally exempt, Q1 2026 | B19: =IF(COUNTIFS('02_MASTER'!$B:$B,"DK.DGP.EXMP.N",'02_MASTER'!$E:$E,2026)=0,"",SUMIFS('02_MASTER'!$F:$F,'02_MASTER'!$B:$B,"DK.DGP.EXMP.N",'02_MASTER'!$E:$E,2026)) | C19: Reported directly by the Agency for Digital Government (DG1).
A20: Citizens formally exempt, April 2025 | B20: =IF(COUNTIFS('02_MASTER'!$B:$B,"DK.DGP.EXMP.N",'02_MASTER'!$E:$E,2025)=0,"",SUMIFS('02_MASTER'!$F:$F,'02_MASTER'!$B:$B,"DK.DGP.EXMP.N",'02_MASTER'!$E:$E,2025)) | C20: Reported as approximately 256,000 (DG1).
A21: Implied population aged 15+ | B21: =IF(COUNTIFS('02_MASTER'!$B:$B,"DK.DGP.EXMP.N",'02_MASTER'!$E:$E,2026)=0,"",SUMIFS('02_MASTER'!$F:$F,'02_MASTER'!$B:$B,"DK.DGP.EXMP.N",'02_MASTER'!$E:$E,2026))/(IF(COUNTIFS('02_MASTER'!$B:$B,"DK.DGP.EXMP",'02_MASTER'!$E:$E,2026)=0,"",SUMIFS('02_MASTER'!$F:$F,'02_MASTER'!$B:$B,"DK.DGP.EXMP",'02_MASTER'!$E:$E,2026))/100) | C21: DERIVED, not retrieved: the exempt headcount divided by the exemption rate. Used only to convert the capability shares below into orders of magnitude. A published 15+ population figure was not verifiable in this session; see 06_RETAIL_GAP.
A22: Implied persons who do not use digital public services at all | B22: =(IF(COUNTIFS('02_MASTER'!$B:$B,"DK.DGX.NOUSE",'02_MASTER'!$E:$E,2026)=0,"",SUMIFS('02_MASTER'!$F:$F,'02_MASTER'!$B:$B,"DK.DGX.NOUSE",'02_MASTER'!$E:$E,2026))/100)*(IF(COUNTIFS('02_MASTER'!$B:$B,"DK.DGP.EXMP.N",'02_MASTER'!$E:$E,2026)=0,"",SUMIFS('02_MASTER'!$F:$F,'02_MASTER'!$B:$B,"DK.DGP.EXMP.N",'02_MASTER'!$E:$E,2026))/(IF(COUNTIFS('02_MASTER'!$B:$B,"DK.DGP.EXMP",'02_MASTER'!$E:$E,2026)=0,"",SUMIFS('02_MASTER'!$F:$F,'02_MASTER'!$B:$B,"DK.DGP.EXMP",'02_MASTER'!$E:$E,2026))/100)) | C22: ORDER OF MAGNITUDE ONLY. Applies a share measured on 'the population' to a 15+ base; the denominators are not identical.
A23: Implied persons facing difficulty with digital public services | B23: =(IF(COUNTIFS('02_MASTER'!$B:$B,"DK.DGX.DIFF",'02_MASTER'!$E:$E,2026)=0,"",SUMIFS('02_MASTER'!$F:$F,'02_MASTER'!$B:$B,"DK.DGX.DIFF",'02_MASTER'!$E:$E,2026))/100)*(IF(COUNTIFS('02_MASTER'!$B:$B,"DK.DGP.EXMP.N",'02_MASTER'!$E:$E,2026)=0,"",SUMIFS('02_MASTER'!$F:$F,'02_MASTER'!$B:$B,"DK.DGP.EXMP.N",'02_MASTER'!$E:$E,2026))/(IF(COUNTIFS('02_MASTER'!$B:$B,"DK.DGP.EXMP",'02_MASTER'!$E:$E,2026)=0,"",SUMIFS('02_MASTER'!$F:$F,'02_MASTER'!$B:$B,"DK.DGP.EXMP",'02_MASTER'!$E:$E,2026))/100)) | C23: ORDER OF MAGNITUDE ONLY, same caveat.
A25: POLICY EVENTS ON THIS SERIES
A26: date | B26: precision | C26: instrument | D26: citation | E26: source
A27: 2012-06-11 | B27: day | C27: Lov om Offentlig Digital Post adopted | D27: LOV nr 528 af 11/06/2012 | E27: RI1
A28: 2014-11-01 | B28: day | C28: Digital Post becomes mandatory for citizens aged 15+ | D28: Lov om Offentlig Digital Post | E28: DG4
A30: Sources: DG1, DG2, EC1, JU1. Reading: the measures are nested rather than contradictory. Formal exemption (4.7%) is an administrative status; the capability measures are three to five times larger. The statutory exemption regime therefore reaches only a minority of the citizens the state's own agency counts as struggling. Which measure is chosen determines the conclusion - so the choice must be argued, not assumed.

Sheet F5_EU27
A1: Figure 5 - Individuals who bought online, 2024
A2: All 27 member states and the EU-27 aggregate, ranked. Denominator: % of internet users.
E3: Individuals who bought online, 2024
A4: country | B4: % | C4: series_code | E4: Denmark in blue, EU-27 aggregate in navy, member states in grey. Ranked descending.
A5: Ireland | B5: =IF(COUNTIFS('02_MASTER'!$B:$B,"IE.ECM.IND.BUY",'02_MASTER'!$E:$E,2024)=0,"",SUMIFS('02_MASTER'!$F:$F,'02_MASTER'!$B:$B,"IE.ECM.IND.BUY",'02_MASTER'!$E:$E,2024)) | C5: IE.ECM.IND.BUY
A6: Netherlands | B6: =IF(COUNTIFS('02_MASTER'!$B:$B,"NL.ECM.IND.BUY",'02_MASTER'!$E:$E,2024)=0,"",SUMIFS('02_MASTER'!$F:$F,'02_MASTER'!$B:$B,"NL.ECM.IND.BUY",'02_MASTER'!$E:$E,2024)) | C6: NL.ECM.IND.BUY
A7: Denmark | B7: =IF(COUNTIFS('02_MASTER'!$B:$B,"DK.ECM.IND.BUY",'02_MASTER'!$E:$E,2024)=0,"",SUMIFS('02_MASTER'!$F:$F,'02_MASTER'!$B:$B,"DK.ECM.IND.BUY",'02_MASTER'!$E:$E,2024)) | C7: DK.ECM.IND.BUY
A8: Sweden | B8: =IF(COUNTIFS('02_MASTER'!$B:$B,"SE.ECM.IND.BUY",'02_MASTER'!$E:$E,2024)=0,"",SUMIFS('02_MASTER'!$F:$F,'02_MASTER'!$B:$B,"SE.ECM.IND.BUY",'02_MASTER'!$E:$E,2024)) | C8: SE.ECM.IND.BUY
A9: Czechia | B9: =IF(COUNTIFS('02_MASTER'!$B:$B,"CZ.ECM.IND.BUY",'02_MASTER'!$E:$E,2024)=0,"",SUMIFS('02_MASTER'!$F:$F,'02_MASTER'!$B:$B,"CZ.ECM.IND.BUY",'02_MASTER'!$E:$E,2024)) | C9: CZ.ECM.IND.BUY
A10: Slovakia | B10: =IF(COUNTIFS('02_MASTER'!$B:$B,"SK.ECM.IND.BUY",'02_MASTER'!$E:$E,2024)=0,"",SUMIFS('02_MASTER'!$F:$F,'02_MASTER'!$B:$B,"SK.ECM.IND.BUY",'02_MASTER'!$E:$E,2024)) | C10: SK.ECM.IND.BUY
A11: France | B11: =IF(COUNTIFS('02_MASTER'!$B:$B,"FR.ECM.IND.BUY",'02_MASTER'!$E:$E,2024)=0,"",SUMIFS('02_MASTER'!$F:$F,'02_MASTER'!$B:$B,"FR.ECM.IND.BUY",'02_MASTER'!$E:$E,2024)) | C11: FR.ECM.IND.BUY
A12: Germany | B12: =IF(COUNTIFS('02_MASTER'!$B:$B,"DE.ECM.IND.BUY",'02_MASTER'!$E:$E,2024)=0,"",SUMIFS('02_MASTER'!$F:$F,'02_MASTER'!$B:$B,"DE.ECM.IND.BUY",'02_MASTER'!$E:$E,2024)) | C12: DE.ECM.IND.BUY
A13: Luxembourg | B13: =IF(COUNTIFS('02_MASTER'!$B:$B,"LU.ECM.IND.BUY",'02_MASTER'!$E:$E,2024)=0,"",SUMIFS('02_MASTER'!$F:$F,'02_MASTER'!$B:$B,"LU.ECM.IND.BUY",'02_MASTER'!$E:$E,2024)) | C13: LU.ECM.IND.BUY
A14: Finland | B14: =IF(COUNTIFS('02_MASTER'!$B:$B,"FI.ECM.IND.BUY",'02_MASTER'!$E:$E,2024)=0,"",SUMIFS('02_MASTER'!$F:$F,'02_MASTER'!$B:$B,"FI.ECM.IND.BUY",'02_MASTER'!$E:$E,2024)) | C14: FI.ECM.IND.BUY
A15: Belgium | B15: =IF(COUNTIFS('02_MASTER'!$B:$B,"BE.ECM.IND.BUY",'02_MASTER'!$E:$E,2024)=0,"",SUMIFS('02_MASTER'!$F:$F,'02_MASTER'!$B:$B,"BE.ECM.IND.BUY",'02_MASTER'!$E:$E,2024)) | C15: BE.ECM.IND.BUY
A16: Hungary | B16: =IF(COUNTIFS('02_MASTER'!$B:$B,"HU.ECM.IND.BUY",'02_MASTER'!$E:$E,2024)=0,"",SUMIFS('02_MASTER'!$F:$F,'02_MASTER'!$B:$B,"HU.ECM.IND.BUY",'02_MASTER'!$E:$E,2024)) | C16: HU.ECM.IND.BUY
A17: Estonia | B17: =IF(COUNTIFS('02_MASTER'!$B:$B,"EE.ECM.IND.BUY",'02_MASTER'!$E:$E,2024)=0,"",SUMIFS('02_MASTER'!$F:$F,'02_MASTER'!$B:$B,"EE.ECM.IND.BUY",'02_MASTER'!$E:$E,2024)) | C17: EE.ECM.IND.BUY
A18: EU-27 average | B18: =IF(COUNTIFS('02_MASTER'!$B:$B,"EU.ECM.IND.BUY",'02_MASTER'!$E:$E,2024)=0,"",SUMIFS('02_MASTER'!$F:$F,'02_MASTER'!$B:$B,"EU.ECM.IND.BUY",'02_MASTER'!$E:$E,2024)) | C18: EU.ECM.IND.BUY
A19: Poland | B19: =IF(COUNTIFS('02_MASTER'!$B:$B,"PL.ECM.IND.BUY",'02_MASTER'!$E:$E,2024)=0,"",SUMIFS('02_MASTER'!$F:$F,'02_MASTER'!$B:$B,"PL.ECM.IND.BUY",'02_MASTER'!$E:$E,2024)) | C19: PL.ECM.IND.BUY
A20: Greece | B20: =IF(COUNTIFS('02_MASTER'!$B:$B,"EL.ECM.IND.BUY",'02_MASTER'!$E:$E,2024)=0,"",SUMIFS('02_MASTER'!$F:$F,'02_MASTER'!$B:$B,"EL.ECM.IND.BUY",'02_MASTER'!$E:$E,2024)) | C20: EL.ECM.IND.BUY
A21: Austria | B21: =IF(COUNTIFS('02_MASTER'!$B:$B,"AT.ECM.IND.BUY",'02_MASTER'!$E:$E,2024)=0,"",SUMIFS('02_MASTER'!$F:$F,'02_MASTER'!$B:$B,"AT.ECM.IND.BUY",'02_MASTER'!$E:$E,2024)) | C21: AT.ECM.IND.BUY
A22: Malta | B22: =IF(COUNTIFS('02_MASTER'!$B:$B,"MT.ECM.IND.BUY",'02_MASTER'!$E:$E,2024)=0,"",SUMIFS('02_MASTER'!$F:$F,'02_MASTER'!$B:$B,"MT.ECM.IND.BUY",'02_MASTER'!$E:$E,2024)) | C22: MT.ECM.IND.BUY
A23: Slovenia | B23: =IF(COUNTIFS('02_MASTER'!$B:$B,"SI.ECM.IND.BUY",'02_MASTER'!$E:$E,2024)=0,"",SUMIFS('02_MASTER'!$F:$F,'02_MASTER'!$B:$B,"SI.ECM.IND.BUY",'02_MASTER'!$E:$E,2024)) | C23: SI.ECM.IND.BUY
A24: Lithuania | B24: =IF(COUNTIFS('02_MASTER'!$B:$B,"LT.ECM.IND.BUY",'02_MASTER'!$E:$E,2024)=0,"",SUMIFS('02_MASTER'!$F:$F,'02_MASTER'!$B:$B,"LT.ECM.IND.BUY",'02_MASTER'!$E:$E,2024)) | C24: LT.ECM.IND.BUY
A25: Spain | B25: =IF(COUNTIFS('02_MASTER'!$B:$B,"ES.ECM.IND.BUY",'02_MASTER'!$E:$E,2024)=0,"",SUMIFS('02_MASTER'!$F:$F,'02_MASTER'!$B:$B,"ES.ECM.IND.BUY",'02_MASTER'!$E:$E,2024)) | C25: ES.ECM.IND.BUY
A26: Croatia | B26: =IF(COUNTIFS('02_MASTER'!$B:$B,"HR.ECM.IND.BUY",'02_MASTER'!$E:$E,2024)=0,"",SUMIFS('02_MASTER'!$F:$F,'02_MASTER'!$B:$B,"HR.ECM.IND.BUY",'02_MASTER'!$E:$E,2024)) | C26: HR.ECM.IND.BUY
A27: Latvia | B27: =IF(COUNTIFS('02_MASTER'!$B:$B,"LV.ECM.IND.BUY",'02_MASTER'!$E:$E,2024)=0,"",SUMIFS('02_MASTER'!$F:$F,'02_MASTER'!$B:$B,"LV.ECM.IND.BUY",'02_MASTER'!$E:$E,2024)) | C27: LV.ECM.IND.BUY
A28: Cyprus | B28: =IF(COUNTIFS('02_MASTER'!$B:$B,"CY.ECM.IND.BUY",'02_MASTER'!$E:$E,2024)=0,"",SUMIFS('02_MASTER'!$F:$F,'02_MASTER'!$B:$B,"CY.ECM.IND.BUY",'02_MASTER'!$E:$E,2024)) | C28: CY.ECM.IND.BUY
A29: Portugal | B29: =IF(COUNTIFS('02_MASTER'!$B:$B,"PT.ECM.IND.BUY",'02_MASTER'!$E:$E,2024)=0,"",SUMIFS('02_MASTER'!$F:$F,'02_MASTER'!$B:$B,"PT.ECM.IND.BUY",'02_MASTER'!$E:$E,2024)) | C29: PT.ECM.IND.BUY
A30: Romania | B30: =IF(COUNTIFS('02_MASTER'!$B:$B,"RO.ECM.IND.BUY",'02_MASTER'!$E:$E,2024)=0,"",SUMIFS('02_MASTER'!$F:$F,'02_MASTER'!$B:$B,"RO.ECM.IND.BUY",'02_MASTER'!$E:$E,2024)) | C30: RO.ECM.IND.BUY
A31: Italy | B31: =IF(COUNTIFS('02_MASTER'!$B:$B,"IT.ECM.IND.BUY",'02_MASTER'!$E:$E,2024)=0,"",SUMIFS('02_MASTER'!$F:$F,'02_MASTER'!$B:$B,"IT.ECM.IND.BUY",'02_MASTER'!$E:$E,2024)) | C31: IT.ECM.IND.BUY
A32: Bulgaria | B32: =IF(COUNTIFS('02_MASTER'!$B:$B,"BG.ECM.IND.BUY",'02_MASTER'!$E:$E,2024)=0,"",SUMIFS('02_MASTER'!$F:$F,'02_MASTER'!$B:$B,"BG.ECM.IND.BUY",'02_MASTER'!$E:$E,2024)) | C32: BG.ECM.IND.BUY
A34: Source: Eurostat isoc_ec_ib20, complete databrowser extract for 2024 (ES7), unrounded. This replaces an earlier 8-country version built from rounded press-release figures; on those the Italian and Romanian values both read 60% and appeared tied, while unrounded Italy is second lowest at 59.60 and Romania is above it at 59.73. Bulgaria remains the lowest of the 27 at 57.18. The ranking above is computed from the data at build time, so it cannot fall out of step with 02_MASTER. Denominator is % of internet users, not % of individuals - see 04_DEFINITIONS.

Sheet F6_ADOPT_BENEFIT
A1: Figure 6 - Does more digital adoption mean more economic activity?
A2: EU cross-section, 2024. X = consumer adoption. Y = share of enterprise turnover from e-sales.
F3: Digital adoption and e-commerce turnover, EU 2024
A4: country | B4: code | C4: X: individuals buying online (%) | D4: Y: e-sales share of turnover (%) | F4: One point per member state with both measures. Fitted by ordinary least squares; see the statistics below.
A5: Austria | B5: AT | C5: =IF(COUNTIFS('02_MASTER'!$B:$B,"AT.ECM.IND.BUY",'02_MASTER'!$E:$E,2024)=0,"",SUMIFS('02_MASTER'!$F:$F,'02_MASTER'!$B:$B,"AT.ECM.IND.BUY",'02_MASTER'!$E:$E,2024)) | D5: =IF(COUNTIFS('02_MASTER'!$B:$B,"AT.ECM.ENT.TRN",'02_MASTER'!$E:$E,2024)=0,"",SUMIFS('02_MASTER'!$F:$F,'02_MASTER'!$B:$B,"AT.ECM.ENT.TRN",'02_MASTER'!$E:$E,2024))
A6: Belgium | B6: BE | C6: =IF(COUNTIFS('02_MASTER'!$B:$B,"BE.ECM.IND.BUY",'02_MASTER'!$E:$E,2024)=0,"",SUMIFS('02_MASTER'!$F:$F,'02_MASTER'!$B:$B,"BE.ECM.IND.BUY",'02_MASTER'!$E:$E,2024)) | D6: =IF(COUNTIFS('02_MASTER'!$B:$B,"BE.ECM.ENT.TRN",'02_MASTER'!$E:$E,2024)=0,"",SUMIFS('02_MASTER'!$F:$F,'02_MASTER'!$B:$B,"BE.ECM.ENT.TRN",'02_MASTER'!$E:$E,2024))
A7: Bulgaria | B7: BG | C7: =IF(COUNTIFS('02_MASTER'!$B:$B,"BG.ECM.IND.BUY",'02_MASTER'!$E:$E,2024)=0,"",SUMIFS('02_MASTER'!$F:$F,'02_MASTER'!$B:$B,"BG.ECM.IND.BUY",'02_MASTER'!$E:$E,2024)) | D7: =IF(COUNTIFS('02_MASTER'!$B:$B,"BG.ECM.ENT.TRN",'02_MASTER'!$E:$E,2024)=0,"",SUMIFS('02_MASTER'!$F:$F,'02_MASTER'!$B:$B,"BG.ECM.ENT.TRN",'02_MASTER'!$E:$E,2024))
A8: Cyprus | B8: CY | C8: =IF(COUNTIFS('02_MASTER'!$B:$B,"CY.ECM.IND.BUY",'02_MASTER'!$E:$E,2024)=0,"",SUMIFS('02_MASTER'!$F:$F,'02_MASTER'!$B:$B,"CY.ECM.IND.BUY",'02_MASTER'!$E:$E,2024)) | D8: =IF(COUNTIFS('02_MASTER'!$B:$B,"CY.ECM.ENT.TRN",'02_MASTER'!$E:$E,2024)=0,"",SUMIFS('02_MASTER'!$F:$F,'02_MASTER'!$B:$B,"CY.ECM.ENT.TRN",'02_MASTER'!$E:$E,2024))
A9: Czechia | B9: CZ | C9: =IF(COUNTIFS('02_MASTER'!$B:$B,"CZ.ECM.IND.BUY",'02_MASTER'!$E:$E,2024)=0,"",SUMIFS('02_MASTER'!$F:$F,'02_MASTER'!$B:$B,"CZ.ECM.IND.BUY",'02_MASTER'!$E:$E,2024)) | D9: =IF(COUNTIFS('02_MASTER'!$B:$B,"CZ.ECM.ENT.TRN",'02_MASTER'!$E:$E,2024)=0,"",SUMIFS('02_MASTER'!$F:$F,'02_MASTER'!$B:$B,"CZ.ECM.ENT.TRN",'02_MASTER'!$E:$E,2024))
A10: Germany | B10: DE | C10: =IF(COUNTIFS('02_MASTER'!$B:$B,"DE.ECM.IND.BUY",'02_MASTER'!$E:$E,2024)=0,"",SUMIFS('02_MASTER'!$F:$F,'02_MASTER'!$B:$B,"DE.ECM.IND.BUY",'02_MASTER'!$E:$E,2024)) | D10: =IF(COUNTIFS('02_MASTER'!$B:$B,"DE.ECM.ENT.TRN",'02_MASTER'!$E:$E,2024)=0,"",SUMIFS('02_MASTER'!$F:$F,'02_MASTER'!$B:$B,"DE.ECM.ENT.TRN",'02_MASTER'!$E:$E,2024))
A11: Denmark | B11: DK | C11: =IF(COUNTIFS('02_MASTER'!$B:$B,"DK.ECM.IND.BUY",'02_MASTER'!$E:$E,2024)=0,"",SUMIFS('02_MASTER'!$F:$F,'02_MASTER'!$B:$B,"DK.ECM.IND.BUY",'02_MASTER'!$E:$E,2024)) | D11: =IF(COUNTIFS('02_MASTER'!$B:$B,"DK.ECM.ENT.TRN",'02_MASTER'!$E:$E,2024)=0,"",SUMIFS('02_MASTER'!$F:$F,'02_MASTER'!$B:$B,"DK.ECM.ENT.TRN",'02_MASTER'!$E:$E,2024))
A12: Spain | B12: ES | C12: =IF(COUNTIFS('02_MASTER'!$B:$B,"ES.ECM.IND.BUY",'02_MASTER'!$E:$E,2024)=0,"",SUMIFS('02_MASTER'!$F:$F,'02_MASTER'!$B:$B,"ES.ECM.IND.BUY",'02_MASTER'!$E:$E,2024)) | D12: =IF(COUNTIFS('02_MASTER'!$B:$B,"ES.ECM.ENT.TRN",'02_MASTER'!$E:$E,2024)=0,"",SUMIFS('02_MASTER'!$F:$F,'02_MASTER'!$B:$B,"ES.ECM.ENT.TRN",'02_MASTER'!$E:$E,2024))
A13: France | B13: FR | C13: =IF(COUNTIFS('02_MASTER'!$B:$B,"FR.ECM.IND.BUY",'02_MASTER'!$E:$E,2024)=0,"",SUMIFS('02_MASTER'!$F:$F,'02_MASTER'!$B:$B,"FR.ECM.IND.BUY",'02_MASTER'!$E:$E,2024)) | D13: =IF(COUNTIFS('02_MASTER'!$B:$B,"FR.ECM.ENT.TRN",'02_MASTER'!$E:$E,2024)=0,"",SUMIFS('02_MASTER'!$F:$F,'02_MASTER'!$B:$B,"FR.ECM.ENT.TRN",'02_MASTER'!$E:$E,2024))
A14: Croatia | B14: HR | C14: =IF(COUNTIFS('02_MASTER'!$B:$B,"HR.ECM.IND.BUY",'02_MASTER'!$E:$E,2024)=0,"",SUMIFS('02_MASTER'!$F:$F,'02_MASTER'!$B:$B,"HR.ECM.IND.BUY",'02_MASTER'!$E:$E,2024)) | D14: =IF(COUNTIFS('02_MASTER'!$B:$B,"HR.ECM.ENT.TRN",'02_MASTER'!$E:$E,2024)=0,"",SUMIFS('02_MASTER'!$F:$F,'02_MASTER'!$B:$B,"HR.ECM.ENT.TRN",'02_MASTER'!$E:$E,2024))
A15: Hungary | B15: HU | C15: =IF(COUNTIFS('02_MASTER'!$B:$B,"HU.ECM.IND.BUY",'02_MASTER'!$E:$E,2024)=0,"",SUMIFS('02_MASTER'!$F:$F,'02_MASTER'!$B:$B,"HU.ECM.IND.BUY",'02_MASTER'!$E:$E,2024)) | D15: =IF(COUNTIFS('02_MASTER'!$B:$B,"HU.ECM.ENT.TRN",'02_MASTER'!$E:$E,2024)=0,"",SUMIFS('02_MASTER'!$F:$F,'02_MASTER'!$B:$B,"HU.ECM.ENT.TRN",'02_MASTER'!$E:$E,2024))
A16: Ireland | B16: IE | C16: =IF(COUNTIFS('02_MASTER'!$B:$B,"IE.ECM.IND.BUY",'02_MASTER'!$E:$E,2024)=0,"",SUMIFS('02_MASTER'!$F:$F,'02_MASTER'!$B:$B,"IE.ECM.IND.BUY",'02_MASTER'!$E:$E,2024)) | D16: =IF(COUNTIFS('02_MASTER'!$B:$B,"IE.ECM.ENT.TRN",'02_MASTER'!$E:$E,2024)=0,"",SUMIFS('02_MASTER'!$F:$F,'02_MASTER'!$B:$B,"IE.ECM.ENT.TRN",'02_MASTER'!$E:$E,2024))
A17: Italy | B17: IT | C17: =IF(COUNTIFS('02_MASTER'!$B:$B,"IT.ECM.IND.BUY",'02_MASTER'!$E:$E,2024)=0,"",SUMIFS('02_MASTER'!$F:$F,'02_MASTER'!$B:$B,"IT.ECM.IND.BUY",'02_MASTER'!$E:$E,2024)) | D17: =IF(COUNTIFS('02_MASTER'!$B:$B,"IT.ECM.ENT.TRN",'02_MASTER'!$E:$E,2024)=0,"",SUMIFS('02_MASTER'!$F:$F,'02_MASTER'!$B:$B,"IT.ECM.ENT.TRN",'02_MASTER'!$E:$E,2024))
A18: Luxembourg | B18: LU | C18: =IF(COUNTIFS('02_MASTER'!$B:$B,"LU.ECM.IND.BUY",'02_MASTER'!$E:$E,2024)=0,"",SUMIFS('02_MASTER'!$F:$F,'02_MASTER'!$B:$B,"LU.ECM.IND.BUY",'02_MASTER'!$E:$E,2024)) | D18: =IF(COUNTIFS('02_MASTER'!$B:$B,"LU.ECM.ENT.TRN",'02_MASTER'!$E:$E,2024)=0,"",SUMIFS('02_MASTER'!$F:$F,'02_MASTER'!$B:$B,"LU.ECM.ENT.TRN",'02_MASTER'!$E:$E,2024))
A19: Malta | B19: MT | C19: =IF(COUNTIFS('02_MASTER'!$B:$B,"MT.ECM.IND.BUY",'02_MASTER'!$E:$E,2024)=0,"",SUMIFS('02_MASTER'!$F:$F,'02_MASTER'!$B:$B,"MT.ECM.IND.BUY",'02_MASTER'!$E:$E,2024)) | D19: =IF(COUNTIFS('02_MASTER'!$B:$B,"MT.ECM.ENT.TRN",'02_MASTER'!$E:$E,2024)=0,"",SUMIFS('02_MASTER'!$F:$F,'02_MASTER'!$B:$B,"MT.ECM.ENT.TRN",'02_MASTER'!$E:$E,2024))
A20: Poland | B20: PL | C20: =IF(COUNTIFS('02_MASTER'!$B:$B,"PL.ECM.IND.BUY",'02_MASTER'!$E:$E,2024)=0,"",SUMIFS('02_MASTER'!$F:$F,'02_MASTER'!$B:$B,"PL.ECM.IND.BUY",'02_MASTER'!$E:$E,2024)) | D20: =IF(COUNTIFS('02_MASTER'!$B:$B,"PL.ECM.ENT.TRN",'02_MASTER'!$E:$E,2024)=0,"",SUMIFS('02_MASTER'!$F:$F,'02_MASTER'!$B:$B,"PL.ECM.ENT.TRN",'02_MASTER'!$E:$E,2024))
A21: Sweden | B21: SE | C21: =IF(COUNTIFS('02_MASTER'!$B:$B,"SE.ECM.IND.BUY",'02_MASTER'!$E:$E,2024)=0,"",SUMIFS('02_MASTER'!$F:$F,'02_MASTER'!$B:$B,"SE.ECM.IND.BUY",'02_MASTER'!$E:$E,2024)) | D21: =IF(COUNTIFS('02_MASTER'!$B:$B,"SE.ECM.ENT.TRN",'02_MASTER'!$E:$E,2024)=0,"",SUMIFS('02_MASTER'!$F:$F,'02_MASTER'!$B:$B,"SE.ECM.ENT.TRN",'02_MASTER'!$E:$E,2024))
A22: Slovenia | B22: SI | C22: =IF(COUNTIFS('02_MASTER'!$B:$B,"SI.ECM.IND.BUY",'02_MASTER'!$E:$E,2024)=0,"",SUMIFS('02_MASTER'!$F:$F,'02_MASTER'!$B:$B,"SI.ECM.IND.BUY",'02_MASTER'!$E:$E,2024)) | D22: =IF(COUNTIFS('02_MASTER'!$B:$B,"SI.ECM.ENT.TRN",'02_MASTER'!$E:$E,2024)=0,"",SUMIFS('02_MASTER'!$F:$F,'02_MASTER'!$B:$B,"SI.ECM.ENT.TRN",'02_MASTER'!$E:$E,2024))
A24: FITTED LINE (ordinary least squares)
A25: statistic | B25: value | C25: reading
A26: n (countries) | B26: =COUNT($C$5:$C$22) | C26: Number of complete X-Y pairs. Expands automatically as data is added.
A27: Slope | B27: =SLOPE($D$5:$D$22,$C$5:$C$22) | C27: Percentage points of enterprise turnover per percentage point of consumer adoption.
A28: Intercept | B28: =INTERCEPT($D$5:$D$22,$C$5:$C$22) | C28: Not interpretable - no country has zero adoption, so this is far outside the observed range.
A29: Correlation (r) | B29: =CORREL($C$5:$C$22,$D$5:$D$22) | C29: Strength and direction of the linear association.
A30: R-squared | B30: =RSQ($D$5:$D$22,$C$5:$C$22) | C30: Share of cross-country variation in Y that moves with X. Estimated on the complete set of paired member states, so it is quotable - see the SAMPLE block below for what the earlier tail-selected sample claimed.
A31: Slope standard error | B31: =STEYX($D$5:$D$22,$C$5:$C$22)/SQRT(DEVSQ($C$5:$C$22)) | C31: Precision of the slope estimate.
A32: Slope t-statistic | B32: =SLOPE($D$5:$D$22,$C$5:$C$22)/(STEYX($D$5:$D$22,$C$5:$C$22)/SQRT(DEVSQ($C$5:$C$22))) | C32: Slope divided by its standard error, on n-2 degrees of freedom. Above about 2.1 the slope is distinguishable from zero at the 5% level on this sample size.
A33: Denmark: actual Y | B33: =IF(COUNTIFS('02_MASTER'!$B:$B,"DK.ECM.ENT.TRN",'02_MASTER'!$E:$E,2024)=0,"",SUMIFS('02_MASTER'!$F:$F,'02_MASTER'!$B:$B,"DK.ECM.ENT.TRN",'02_MASTER'!$E:$E,2024)) | C33: Denmark's observed value.
A34: Denmark: fitted Y | B34: =INTERCEPT($D$5:$D$22,$C$5:$C$22)+SLOPE($D$5:$D$22,$C$5:$C$22)*IF(COUNTIFS('02_MASTER'!$B:$B,"DK.ECM.IND.BUY",'02_MASTER'!$E:$E,2024)=0,"",SUMIFS('02_MASTER'!$F:$F,'02_MASTER'!$B:$B,"DK.ECM.IND.BUY",'02_MASTER'!$E:$E,2024)) | C34: What the line predicts for Denmark's adoption level.
A35: Denmark: residual | B35: =IF(COUNTIFS('02_MASTER'!$B:$B,"DK.ECM.ENT.TRN",'02_MASTER'!$E:$E,2024)=0,"",SUMIFS('02_MASTER'!$F:$F,'02_MASTER'!$B:$B,"DK.ECM.ENT.TRN",'02_MASTER'!$E:$E,2024))-(INTERCEPT($D$5:$D$22,$C$5:$C$22)+SLOPE($D$5:$D$22,$C$5:$C$22)*IF(COUNTIFS('02_MASTER'!$B:$B,"DK.ECM.IND.BUY",'02_MASTER'!$E:$E,2024)=0,"",SUMIFS('02_MASTER'!$F:$F,'02_MASTER'!$B:$B,"DK.ECM.IND.BUY",'02_MASTER'!$E:$E,2024))) | C35: Positive: Denmark converts adoption into commercial activity better than the EU pattern predicts. Negative: worse.
A37: SAMPLE - how these points were obtained
A38: COMPLETE FOR 2024: the X column is the full Eurostat isoc_ec_ib20 extract for all 27 member states, unrounded, taken from the databrowser. Every member state holding both measures is plotted - 18 of them. No country with both values is excluded, so the fit is no longer conditioned on where a country sits in the ranking.
A39: WHAT THE EARLIER SAMPLE CLAIMED: an earlier version of this figure drew X from a Eurostat press release, which named only the three highest countries, the three lowest and two large movers. On those 6 tail countries the fit was R-squared 0.853 with a slope of +0.655. On the complete cross-section it is R-squared 0.674 with a slope of +0.602.
A40: READING THAT COMPARISON: the slope moved by about 8% while R-squared fell by 0.18. This is the signature of selection on the tails - it widens the spread in X relative to the scatter around the line, which flatters the fit while leaving the estimated relationship roughly intact. The earlier R-squared was an upper bound, as the warning it replaced said; this one is an estimate.
A41: STILL NOT A COMPLETE CROSS-SECTION OF THE EU: nine member states hold the adoption measure but not the enterprise turnover measure and are listed below. The sample is complete with respect to X and incomplete with respect to Y, so it is 18 countries rather than 27 - but the countries dropped are dropped by data availability, not by their position on either axis.
A42: DIRECTION OF CAUSATION IS NOT ESTABLISHED AND CANNOT BE. X measures consumers; Y measures enterprises, including business-to-business sales that no consumer touches. Both plausibly rise with national income, which is in neither axis. This figure shows that digital commerce runs deep in the same economies where consumers buy online. It does not show that the one produces the other.
A44: AWAITING DATA - not plotted
A45: country | B45: code | C45: missing
A46: Estonia | B46: EE | C46: Y - add EE.ECM.ENT.TRN for 2024 (Eurostat tin00110)
A47: Greece | B47: EL | C47: Y - add EL.ECM.ENT.TRN for 2024 (Eurostat tin00110)
A48: Finland | B48: FI | C48: Y - add FI.ECM.ENT.TRN for 2024 (Eurostat tin00110)
A49: Lithuania | B49: LT | C49: Y - add LT.ECM.ENT.TRN for 2024 (Eurostat tin00110)
A50: Latvia | B50: LV | C50: Y - add LV.ECM.ENT.TRN for 2024 (Eurostat tin00110)
A51: Netherlands | B51: NL | C51: Y - add NL.ECM.ENT.TRN for 2024 (Eurostat tin00110)
A52: Portugal | B52: PT | C52: Y - add PT.ECM.ENT.TRN for 2024 (Eurostat tin00110)
A53: Romania | B53: RO | C53: Y - add RO.ECM.ENT.TRN for 2024 (Eurostat tin00110)
A54: Slovakia | B54: SK | C54: Y - add SK.ECM.ENT.TRN for 2024 (Eurostat tin00110)
A56: Sources: Eurostat isoc_ec_ib20 (ES7) for X; Eurostat tin00110 (ES5, ES6) for Y. WHY A CROSS-SECTION: the Danish adoption and outcome series share almost no observation years - the best time-series pairing in this dataset is n=2 - so a within-Denmark scatter of adoption against outcome cannot be drawn from verified data. SAMPLE: n=18 of 27 member states. This is a small sample; report the association descriptively and do not quote a p-value. Adding the missing values listed above raises n automatically on the next rebuild. WHAT Y MEASURES: tin00110 covers all enterprises with 10+ employees outside the financial sector, so it includes B2B and EDI ordering across every industry, not retail alone. X is a consumer measure. The two sit on different sides of the market, so a positive association is evidence that digital commerce is deep in an economy - not evidence that consumers buying online causes enterprise turnover.

Sheet F7_QUALITY
A1: Figure 7 - Denmark vs the EU: adoption and capability, then quality
A2: Leads on every capability measure. Below average on citizen service quality.
F3: Denmark vs EU-27 average
A4: indicator | B4: Denmark | C4: EU-27 | D4: unit | F4: Denmark in blue, EU average in grey. Note the direction reverses on the bottom two rows.
A5: SMEs with at least basic digital intensity | B5: =IF(COUNTIFS('02_MASTER'!$B:$B,"DK.ENT.DII",'02_MASTER'!$E:$E,2025)=0,"",SUMIFS('02_MASTER'!$F:$F,'02_MASTER'!$B:$B,"DK.ENT.DII",'02_MASTER'!$E:$E,2025)) | C5: =IF(COUNTIFS('02_MASTER'!$B:$B,"EU.ENT.DII",'02_MASTER'!$E:$E,2025)=0,"",SUMIFS('02_MASTER'!$F:$F,'02_MASTER'!$B:$B,"EU.ENT.DII",'02_MASTER'!$E:$E,2025)) | D5: % of SMEs
A6: Enterprises adopting AI | B6: =IF(COUNTIFS('02_MASTER'!$B:$B,"DK.ENT.AI",'02_MASTER'!$E:$E,2025)=0,"",SUMIFS('02_MASTER'!$F:$F,'02_MASTER'!$B:$B,"DK.ENT.AI",'02_MASTER'!$E:$E,2025)) | D6: % of enterprises (EU avg 19.95)
A7: Digital public services for citizens | B7: =IF(COUNTIFS('02_MASTER'!$B:$B,"DK.GOV.DPS.CIT",'02_MASTER'!$E:$E,2025)=0,"",SUMIFS('02_MASTER'!$F:$F,'02_MASTER'!$B:$B,"DK.GOV.DPS.CIT",'02_MASTER'!$E:$E,2025)) | C7: =IF(COUNTIFS('02_MASTER'!$B:$B,"EU.GOV.DPS.CIT",'02_MASTER'!$E:$E,2025)=0,"",SUMIFS('02_MASTER'!$F:$F,'02_MASTER'!$B:$B,"EU.GOV.DPS.CIT",'02_MASTER'!$E:$E,2025)) | D7: eGovernment Benchmark score 0-100
A8: Cross-border digital public services | B8: =IF(COUNTIFS('02_MASTER'!$B:$B,"DK.GOV.DPS.XB",'02_MASTER'!$E:$E,2025)=0,"",SUMIFS('02_MASTER'!$F:$F,'02_MASTER'!$B:$B,"DK.GOV.DPS.XB",'02_MASTER'!$E:$E,2025)) | D8: score 0-100 (EU avg 75.28)
A10: THE GAP THAT MATTERS - service quality, not capability
A11: quantity | B11: value | C11: reading
A12: Digital public services, DK minus EU average | B12: =IF(COUNTIFS('02_MASTER'!$B:$B,"DK.GOV.DPS.CIT",'02_MASTER'!$E:$E,2025)=0,"",SUMIFS('02_MASTER'!$F:$F,'02_MASTER'!$B:$B,"DK.GOV.DPS.CIT",'02_MASTER'!$E:$E,2025))-IF(COUNTIFS('02_MASTER'!$B:$B,"EU.GOV.DPS.CIT",'02_MASTER'!$E:$E,2025)=0,"",SUMIFS('02_MASTER'!$F:$F,'02_MASTER'!$B:$B,"EU.GOV.DPS.CIT",'02_MASTER'!$E:$E,2025)) | C12: Negative. The most digitalised population in the EU receives below-average digital public services.
A13: Digital skills gap within Denmark, 16-24 minus 55-74 | B13: =IF(COUNTIFS('02_MASTER'!$B:$B,"DK.SKL.1624",'02_MASTER'!$E:$E,2025)=0,"",SUMIFS('02_MASTER'!$F:$F,'02_MASTER'!$B:$B,"DK.SKL.1624",'02_MASTER'!$E:$E,2025))-IF(COUNTIFS('02_MASTER'!$B:$B,"DK.SKL.5574",'02_MASTER'!$E:$E,2025)=0,"",SUMIFS('02_MASTER'!$F:$F,'02_MASTER'!$B:$B,"DK.SKL.5574",'02_MASTER'!$E:$E,2025)) | C13: The within-country spread. Note that Denmark's WEAKEST age group (67.81%) still beats the EU average (42.60%) by 25pp, so Danish exclusion is not a skills deficit relative to Europe - it is a mandate calibrated above the bottom of its own distribution.
A14: AI adoption gap within Denmark, large firms minus SMEs | B14: =IF(COUNTIFS('02_MASTER'!$B:$B,"DK.ENT.AI.LRG",'02_MASTER'!$E:$E,2025)=0,"",SUMIFS('02_MASTER'!$F:$F,'02_MASTER'!$B:$B,"DK.ENT.AI.LRG",'02_MASTER'!$E:$E,2025))-IF(COUNTIFS('02_MASTER'!$B:$B,"DK.ENT.AI.SME",'02_MASTER'!$E:$E,2025)=0,"",SUMIFS('02_MASTER'!$F:$F,'02_MASTER'!$B:$B,"DK.ENT.AI.SME",'02_MASTER'!$E:$E,2025)) | C14: Breadth without depth, restated for AI.
A16: Source: European Commission, Digital Decade 2026 country report for Denmark (EC1). CAUTION: the eGovernment Benchmark is a scored assessment, not a survey proportion, and a 2.4-point difference between two scores should not be read as a precisely measured gap. The direction is the finding; the magnitude is not.

Sheet F8_SMVDIGITAL
A1: Figure 8 - SMV:Digital, the one policy with a control group
A2: Danmarks Statistik matched-comparison evaluation, June 2025.
E3: SMV:Digital participant outcomes
A4: measure | B4: value | C4: unit | E4: Participation measures only. No effect size is plotted because none was verified.
A5: Digitalisation projects supported since 2018 | B5: =IF(COUNTIFS('02_MASTER'!$B:$B,"DK.SME.SMVD.PROJ",'02_MASTER'!$E:$E,2025)=0,"",SUMIFS('02_MASTER'!$F:$F,'02_MASTER'!$B:$B,"DK.SME.SMVD.PROJ",'02_MASTER'!$E:$E,2025)) | C5: count
A6: Participants investing further during the project | B6: =IF(COUNTIFS('02_MASTER'!$B:$B,"DK.SME.SMVD.INV",'02_MASTER'!$E:$E,2025)=0,"",SUMIFS('02_MASTER'!$F:$F,'02_MASTER'!$B:$B,"DK.SME.SMVD.INV",'02_MASTER'!$E:$E,2025)) | C6: % of participants
A7: Participants with no further investment plans | B7: =IF(COUNTIFS('02_MASTER'!$B:$B,"DK.SME.SMVD.NOINV",'02_MASTER'!$E:$E,2025)=0,"",SUMIFS('02_MASTER'!$F:$F,'02_MASTER'!$B:$B,"DK.SME.SMVD.NOINV",'02_MASTER'!$E:$E,2025)) | C7: % of participants
A9: WHY THIS IS THE STRONGEST EVIDENCE IN THE WORKBOOK
A10: The evaluation was carried out by Danmarks Statistik, which compared participating firms against comparable firms that did not participate. Participants showed higher revenue AND higher employment.
A11: That is a comparison group. Nothing else in this workbook has one. Figure 6's cross-section can show that adoption and commercial activity move together across countries; it cannot rule out that richer countries simply do more of both. A matched comparison can.
A12: LIMIT: the effect sizes are not reproduced here because they were not verified against the evaluation itself. The direction of the finding is sourced; the magnitude is not, and must not be invented.
A13: LIMIT: participation is voluntary, so selection into the programme by more capable or more ambitious firms is not excluded by matching alone.
A15: POLICY EVENTS ON THIS SERIES
A16: date | B16: precision | C16: instrument | D16: citation | E16: source
A17: 2018-01-01 | B17: year | C17: SMV:Digital launched | D17: Danish digital growth plan for SMEs | E17: DG3
A18: 2026-01-01 | B18: year | C18: SMV:Digital grant pools continue | D18: Tilskudspuljer i 2026 | E18: SMV1
A20: Source: Effektmaaling af SMV:Digital, Danmarks Statistik for the Agency for Digital Government, June 2025 (DG3); scheme status from SMV:Digital's 2026 grant-pool page (SMV1).

Sheet F9_CONSOLIDATION
A1: Figure 9 - Consolidation of Danish retail banking
A2: Three measures of the same structural shift. Note the different start years: the periods are NOT comparable to one another.
J3: Banking consolidation, by measure
A4: measure | B4: period | C4: first | D4: last | E4: change | G4: chart label (helper) | H4: change | J4: Employment in blue - it fell least. Periods differ by measure; read each bar against its own label.
A5: Financial institutions | B5: 1991-2024 | C5: =IF(COUNTIFS('02_MASTER'!$B:$B,"DK.FIN.INST",'02_MASTER'!$E:$E,1991)=0,"",SUMIFS('02_MASTER'!$F:$F,'02_MASTER'!$B:$B,"DK.FIN.INST",'02_MASTER'!$E:$E,1991)) | D5: =IF(COUNTIFS('02_MASTER'!$B:$B,"DK.FIN.INST",'02_MASTER'!$E:$E,2024)=0,"",SUMIFS('02_MASTER'!$F:$F,'02_MASTER'!$B:$B,"DK.FIN.INST",'02_MASTER'!$E:$E,2024)) | E5: =(IF(COUNTIFS('02_MASTER'!$B:$B,"DK.FIN.INST",'02_MASTER'!$E:$E,2024)=0,"",SUMIFS('02_MASTER'!$F:$F,'02_MASTER'!$B:$B,"DK.FIN.INST",'02_MASTER'!$E:$E,2024))/IF(COUNTIFS('02_MASTER'!$B:$B,"DK.FIN.INST",'02_MASTER'!$E:$E,1991)=0,"",SUMIFS('02_MASTER'!$F:$F,'02_MASTER'!$B:$B,"DK.FIN.INST",'02_MASTER'!$E:$E,1991)))-1 | G5: Financial institutions (1991-2024) | H5: =(IF(COUNTIFS('02_MASTER'!$B:$B,"DK.FIN.INST",'02_MASTER'!$E:$E,2024)=0,"",SUMIFS('02_MASTER'!$F:$F,'02_MASTER'!$B:$B,"DK.FIN.INST",'02_MASTER'!$E:$E,2024))/IF(COUNTIFS('02_MASTER'!$B:$B,"DK.FIN.INST",'02_MASTER'!$E:$E,1991)=0,"",SUMIFS('02_MASTER'!$F:$F,'02_MASTER'!$B:$B,"DK.FIN.INST",'02_MASTER'!$E:$E,1991)))-1
A6: Bank branches | B6: 2004-2024 | C6: =IF(COUNTIFS('02_MASTER'!$B:$B,"DK.FIN.BRCH",'02_MASTER'!$E:$E,2004)=0,"",SUMIFS('02_MASTER'!$F:$F,'02_MASTER'!$B:$B,"DK.FIN.BRCH",'02_MASTER'!$E:$E,2004)) | D6: =IF(COUNTIFS('02_MASTER'!$B:$B,"DK.FIN.BRCH",'02_MASTER'!$E:$E,2024)=0,"",SUMIFS('02_MASTER'!$F:$F,'02_MASTER'!$B:$B,"DK.FIN.BRCH",'02_MASTER'!$E:$E,2024)) | E6: =(IF(COUNTIFS('02_MASTER'!$B:$B,"DK.FIN.BRCH",'02_MASTER'!$E:$E,2024)=0,"",SUMIFS('02_MASTER'!$F:$F,'02_MASTER'!$B:$B,"DK.FIN.BRCH",'02_MASTER'!$E:$E,2024))/IF(COUNTIFS('02_MASTER'!$B:$B,"DK.FIN.BRCH",'02_MASTER'!$E:$E,2004)=0,"",SUMIFS('02_MASTER'!$F:$F,'02_MASTER'!$B:$B,"DK.FIN.BRCH",'02_MASTER'!$E:$E,2004)))-1 | G6: Bank branches (2004-2024) | H6: =(IF(COUNTIFS('02_MASTER'!$B:$B,"DK.FIN.BRCH",'02_MASTER'!$E:$E,2024)=0,"",SUMIFS('02_MASTER'!$F:$F,'02_MASTER'!$B:$B,"DK.FIN.BRCH",'02_MASTER'!$E:$E,2024))/IF(COUNTIFS('02_MASTER'!$B:$B,"DK.FIN.BRCH",'02_MASTER'!$E:$E,2004)=0,"",SUMIFS('02_MASTER'!$F:$F,'02_MASTER'!$B:$B,"DK.FIN.BRCH",'02_MASTER'!$E:$E,2004)))-1
A7: Bank employees | B7: 1991-2024 | C7: =IF(COUNTIFS('02_MASTER'!$B:$B,"DK.FIN.EMP",'02_MASTER'!$E:$E,1991)=0,"",SUMIFS('02_MASTER'!$F:$F,'02_MASTER'!$B:$B,"DK.FIN.EMP",'02_MASTER'!$E:$E,1991)) | D7: =IF(COUNTIFS('02_MASTER'!$B:$B,"DK.FIN.EMP",'02_MASTER'!$E:$E,2024)=0,"",SUMIFS('02_MASTER'!$F:$F,'02_MASTER'!$B:$B,"DK.FIN.EMP",'02_MASTER'!$E:$E,2024)) | E7: =(IF(COUNTIFS('02_MASTER'!$B:$B,"DK.FIN.EMP",'02_MASTER'!$E:$E,2024)=0,"",SUMIFS('02_MASTER'!$F:$F,'02_MASTER'!$B:$B,"DK.FIN.EMP",'02_MASTER'!$E:$E,2024))/IF(COUNTIFS('02_MASTER'!$B:$B,"DK.FIN.EMP",'02_MASTER'!$E:$E,1991)=0,"",SUMIFS('02_MASTER'!$F:$F,'02_MASTER'!$B:$B,"DK.FIN.EMP",'02_MASTER'!$E:$E,1991)))-1 | G7: Bank employees (1991-2024) | H7: =(IF(COUNTIFS('02_MASTER'!$B:$B,"DK.FIN.EMP",'02_MASTER'!$E:$E,2024)=0,"",SUMIFS('02_MASTER'!$F:$F,'02_MASTER'!$B:$B,"DK.FIN.EMP",'02_MASTER'!$E:$E,2024))/IF(COUNTIFS('02_MASTER'!$B:$B,"DK.FIN.EMP",'02_MASTER'!$E:$E,1991)=0,"",SUMIFS('02_MASTER'!$F:$F,'02_MASTER'!$B:$B,"DK.FIN.EMP",'02_MASTER'!$E:$E,1991)))-1
A9: THE ASYMMETRY - staff per institution
A10: statistic | B10: 1991 | C10: 2024 | D10: reading
A11: Employees per institution | B11: =IF(COUNTIFS('02_MASTER'!$B:$B,"DK.FIN.EMP",'02_MASTER'!$E:$E,1991)=0,"",SUMIFS('02_MASTER'!$F:$F,'02_MASTER'!$B:$B,"DK.FIN.EMP",'02_MASTER'!$E:$E,1991))/IF(COUNTIFS('02_MASTER'!$B:$B,"DK.FIN.INST",'02_MASTER'!$E:$E,1991)=0,"",SUMIFS('02_MASTER'!$F:$F,'02_MASTER'!$B:$B,"DK.FIN.INST",'02_MASTER'!$E:$E,1991)) | C11: =IF(COUNTIFS('02_MASTER'!$B:$B,"DK.FIN.EMP",'02_MASTER'!$E:$E,2024)=0,"",SUMIFS('02_MASTER'!$F:$F,'02_MASTER'!$B:$B,"DK.FIN.EMP",'02_MASTER'!$E:$E,2024))/IF(COUNTIFS('02_MASTER'!$B:$B,"DK.FIN.INST",'02_MASTER'!$E:$E,2024)=0,"",SUMIFS('02_MASTER'!$F:$F,'02_MASTER'!$B:$B,"DK.FIN.INST",'02_MASTER'!$E:$E,2024)) | D11: Denmark did not shed banking labour in proportion to its institutions. It concentrated it.
A12: Change in staff per institution | B12: =((IF(COUNTIFS('02_MASTER'!$B:$B,"DK.FIN.EMP",'02_MASTER'!$E:$E,2024)=0,"",SUMIFS('02_MASTER'!$F:$F,'02_MASTER'!$B:$B,"DK.FIN.EMP",'02_MASTER'!$E:$E,2024))/IF(COUNTIFS('02_MASTER'!$B:$B,"DK.FIN.INST",'02_MASTER'!$E:$E,2024)=0,"",SUMIFS('02_MASTER'!$F:$F,'02_MASTER'!$B:$B,"DK.FIN.INST",'02_MASTER'!$E:$E,2024)))/(IF(COUNTIFS('02_MASTER'!$B:$B,"DK.FIN.EMP",'02_MASTER'!$E:$E,1991)=0,"",SUMIFS('02_MASTER'!$F:$F,'02_MASTER'!$B:$B,"DK.FIN.EMP",'02_MASTER'!$E:$E,1991))/IF(COUNTIFS('02_MASTER'!$B:$B,"DK.FIN.INST",'02_MASTER'!$E:$E,1991)=0,"",SUMIFS('02_MASTER'!$F:$F,'02_MASTER'!$B:$B,"DK.FIN.INST",'02_MASTER'!$E:$E,1991))))-1 | D12: The measure that rose. Every other line on this sheet falls.
A13: Employees per branch, 2024 | B13: =IF(COUNTIFS('02_MASTER'!$B:$B,"DK.FIN.EMP",'02_MASTER'!$E:$E,2024)=0,"",SUMIFS('02_MASTER'!$F:$F,'02_MASTER'!$B:$B,"DK.FIN.EMP",'02_MASTER'!$E:$E,2024))/IF(COUNTIFS('02_MASTER'!$B:$B,"DK.FIN.BRCH",'02_MASTER'!$E:$E,2024)=0,"",SUMIFS('02_MASTER'!$F:$F,'02_MASTER'!$B:$B,"DK.FIN.BRCH",'02_MASTER'!$E:$E,2024)) | D13: Branch counts begin in 2004, so no 1991 comparison is available for this ratio.
A16: Sources: Finans Danmark (FD1) for institutions, branches and employment. CAUTION ON THE PERIODS: institutions and employment run 1991-2024; branches only 2004-2024. The three percentage changes above are therefore NOT measured over a common window and must not be subtracted from one another. What is comparable is institutions against employment, both 1991-2024: institutions fell by roughly three quarters while employment fell by under a third. Reading: consolidation removed institutions and branches far faster than it removed jobs, so the surviving institutions are much larger. This is a concentration and scale effect, not a labour-shedding one, and it is the economic consequence of digital payment adoption that the branch count alone does not show. Employment figures are rounded by the source - it states 'around 51,000' and 'just under 36,000' - and carry flag e.

Sheet F10_SKILLS
A1: Figure 10 - At least basic digital skills, by age band, 2025
A2: Denmark against the EU-27 average. Same publication, same definition, same year.
F3: At least basic digital skills by age, DK vs EU-27
A4: age band | B4: Denmark | C4: EU-27 | D4: DK lead | F4: Denmark in blue; the EU-27 average in grey. Note that the Danish 55-74 bar still clears the EU average for its own band.
A5: 16-24 | B5: =IF(COUNTIFS('02_MASTER'!$B:$B,"DK.SKL.1624",'02_MASTER'!$E:$E,2025)=0,"",SUMIFS('02_MASTER'!$F:$F,'02_MASTER'!$B:$B,"DK.SKL.1624",'02_MASTER'!$E:$E,2025)) | C5: =IF(COUNTIFS('02_MASTER'!$B:$B,"EU.SKL.1624",'02_MASTER'!$E:$E,2025)=0,"",SUMIFS('02_MASTER'!$F:$F,'02_MASTER'!$B:$B,"EU.SKL.1624",'02_MASTER'!$E:$E,2025)) | D5: =IF(COUNTIFS('02_MASTER'!$B:$B,"DK.SKL.1624",'02_MASTER'!$E:$E,2025)=0,"",SUMIFS('02_MASTER'!$F:$F,'02_MASTER'!$B:$B,"DK.SKL.1624",'02_MASTER'!$E:$E,2025))-IF(COUNTIFS('02_MASTER'!$B:$B,"EU.SKL.1624",'02_MASTER'!$E:$E,2025)=0,"",SUMIFS('02_MASTER'!$F:$F,'02_MASTER'!$B:$B,"EU.SKL.1624",'02_MASTER'!$E:$E,2025))
A6: 25-54 | B6: =IF(COUNTIFS('02_MASTER'!$B:$B,"DK.SKL.2554",'02_MASTER'!$E:$E,2025)=0,"",SUMIFS('02_MASTER'!$F:$F,'02_MASTER'!$B:$B,"DK.SKL.2554",'02_MASTER'!$E:$E,2025)) | C6: =IF(COUNTIFS('02_MASTER'!$B:$B,"EU.SKL.2554",'02_MASTER'!$E:$E,2025)=0,"",SUMIFS('02_MASTER'!$F:$F,'02_MASTER'!$B:$B,"EU.SKL.2554",'02_MASTER'!$E:$E,2025)) | D6: =IF(COUNTIFS('02_MASTER'!$B:$B,"DK.SKL.2554",'02_MASTER'!$E:$E,2025)=0,"",SUMIFS('02_MASTER'!$F:$F,'02_MASTER'!$B:$B,"DK.SKL.2554",'02_MASTER'!$E:$E,2025))-IF(COUNTIFS('02_MASTER'!$B:$B,"EU.SKL.2554",'02_MASTER'!$E:$E,2025)=0,"",SUMIFS('02_MASTER'!$F:$F,'02_MASTER'!$B:$B,"EU.SKL.2554",'02_MASTER'!$E:$E,2025))
A7: 55-74 | B7: =IF(COUNTIFS('02_MASTER'!$B:$B,"DK.SKL.5574",'02_MASTER'!$E:$E,2025)=0,"",SUMIFS('02_MASTER'!$F:$F,'02_MASTER'!$B:$B,"DK.SKL.5574",'02_MASTER'!$E:$E,2025)) | C7: =IF(COUNTIFS('02_MASTER'!$B:$B,"EU.SKL.5574",'02_MASTER'!$E:$E,2025)=0,"",SUMIFS('02_MASTER'!$F:$F,'02_MASTER'!$B:$B,"EU.SKL.5574",'02_MASTER'!$E:$E,2025)) | D7: =IF(COUNTIFS('02_MASTER'!$B:$B,"DK.SKL.5574",'02_MASTER'!$E:$E,2025)=0,"",SUMIFS('02_MASTER'!$F:$F,'02_MASTER'!$B:$B,"DK.SKL.5574",'02_MASTER'!$E:$E,2025))-IF(COUNTIFS('02_MASTER'!$B:$B,"EU.SKL.5574",'02_MASTER'!$E:$E,2025)=0,"",SUMIFS('02_MASTER'!$F:$F,'02_MASTER'!$B:$B,"EU.SKL.5574",'02_MASTER'!$E:$E,2025))
A9: WHY THIS MATTERS FOR THE EXCLUSION ARGUMENT
A10: statistic | B10: value | C10: reading
A11: Danish gradient, 16-24 less 55-74 | B11: =IF(COUNTIFS('02_MASTER'!$B:$B,"DK.SKL.1624",'02_MASTER'!$E:$E,2025)=0,"",SUMIFS('02_MASTER'!$F:$F,'02_MASTER'!$B:$B,"DK.SKL.1624",'02_MASTER'!$E:$E,2025))-IF(COUNTIFS('02_MASTER'!$B:$B,"DK.SKL.5574",'02_MASTER'!$E:$E,2025)=0,"",SUMIFS('02_MASTER'!$F:$F,'02_MASTER'!$B:$B,"DK.SKL.5574",'02_MASTER'!$E:$E,2025)) | C11: The internal spread across Danish age bands.
A12: EU gradient, 16-24 less 55-74 | B12: =IF(COUNTIFS('02_MASTER'!$B:$B,"EU.SKL.1624",'02_MASTER'!$E:$E,2025)=0,"",SUMIFS('02_MASTER'!$F:$F,'02_MASTER'!$B:$B,"EU.SKL.1624",'02_MASTER'!$E:$E,2025))-IF(COUNTIFS('02_MASTER'!$B:$B,"EU.SKL.5574",'02_MASTER'!$E:$E,2025)=0,"",SUMIFS('02_MASTER'!$F:$F,'02_MASTER'!$B:$B,"EU.SKL.5574",'02_MASTER'!$E:$E,2025)) | C12: The same spread for the EU as a whole. Denmark's is the narrower of the two, so its age gradient is comparatively mild.
A13: Danish 55-74 less the EU average for 55-74 | B13: =IF(COUNTIFS('02_MASTER'!$B:$B,"DK.SKL.5574",'02_MASTER'!$E:$E,2025)=0,"",SUMIFS('02_MASTER'!$F:$F,'02_MASTER'!$B:$B,"DK.SKL.5574",'02_MASTER'!$E:$E,2025))-IF(COUNTIFS('02_MASTER'!$B:$B,"EU.SKL.5574",'02_MASTER'!$E:$E,2025)=0,"",SUMIFS('02_MASTER'!$F:$F,'02_MASTER'!$B:$B,"EU.SKL.5574",'02_MASTER'!$E:$E,2025)) | C13: Denmark's weakest band against the EU's same band - NOT against the EU all-ages average. Positive and large.
A15: Source: European Commission, Digital Decade 2026 country report for Denmark (EC1). The three EU-27 values were previously held only in the note field of the Danish rows; they are now observations in 02_MASTER under EU.SKL.*, because a figure in a note cannot be looked up, charted or traced. READING: Denmark leads the EU average in every age band, and its weakest band (55-74) clears the EU average for that same band by a wide margin. The Danish population excluded from digital public services is therefore not explained by low skills relative to Europe - the mandate is calibrated above the bottom of its own distribution. Compare the exclusion measures on F4: 4.7% are formally exempt while 16.5% report difficulty. That gap is administrative, not a capability deficit. Do not compare the 55-74 figure against an EU all-ages average; the comparison is band against the same band.

Sheet 06_RETAIL_GAP
A1: Documented gap - retail trade volume index
A2: Recorded rather than silently omitted.
A4: Status | B4: NOT RETRIEVED
A5: Indicator | B5: Retail trade turnover, volume index (mangdeindeks)
A6: Authority | B6: Danmarks Statistik (DST1); also available via Eurostat sts_trtu_a
A7: Filters required | B7: geo=DK; nace_r2=G47; indic_bt=VOL; s_adj=SCA; unit=I21 (2021=100)
A8: Why not retrieved | B8: Values are published through StatBank and the Eurostat databrowser. This session's network policy blocked direct access to both, and the figure could not be verified by search. A value that cannot be traced is not entered.
A9: Base year caution | B9: Danmarks Statistik rebased the index from 2015=100 to 2021=100. Series retrieved on different bases must not be joined.
A10: Effect on the analysis | B10: The e-commerce section rests on the enterprise e-sales evidence in F3_ESALES instead, which is better sourced. No conclusion in the report depends on this series.
A11: To fill | B11: Retrieve from statistikbanken.dk, add rows to dataset.py under series_code DK.RET.VOL with unit 'index 2021=100', and re-run build_workbook.py.

Sheet 07_LIMITATIONS
A1: Data quality statement
A2: Read before citing any value.
A4: No inferential statistics | B4: The longest series here has six observations. Regression, cointegration and Granger-causality procedures require far more, and any such result on this dataset would be uninterpretable. The workbook supports description and comparison only. Co-movement between digital payment adoption and branch closures is presented as association, never as measured causation.
A5: Figure 6 tail selection - RESOLVED, and what it cost | B5: The adoption column in Figure 6 was originally assembled from a Eurostat press release naming the highest three countries, the lowest three and two large movers, so most plotted points came from the ends of the EU distribution. Selecting on the extremes of X inflates the correlation coefficient regardless of the underlying relationship, and R-squared was withheld from the chart face for that reason. The column is now the complete isoc_ec_ib20 databrowser extract for all 27 member states, unrounded, so the selection is gone and R-squared is displayed. The measured cost of the bias is retained on F6 because it is informative: on the 6 tail countries the fit was R-squared 0.853 with a slope of +0.655; on the complete cross-section it is R-squared 0.674 with a slope of +0.602. Tail selection barely moved the slope and flattered the fit by 0.18.
A6: No price deflator on the turnover series | B6: E-sales as a share of enterprise turnover runs 2014 to 2024, spanning the pandemic and the 2022 inflation episode. Turnover is nominal, and online and physical retail did not face the same price path. Part of the measured rise in the e-sales share is therefore relative price movement rather than real reallocation of activity. No deflator was available in this session and none has been applied, so the doubling of intensity should be read as nominal.
A7: Banking series use different base years | B7: This constrains F9_CONSOLIDATION directly: the three percentage changes on that sheet are not measured over a common window, so they must not be differenced against one another. Institutions and employment are comparable to each other, both 1991-2024. Branch counts begin in 2004; institution counts and employment begin in 1991. A 2004-2024 branch change and a 1991-2024 employment change are not comparable, and placing the two percentages side by side in prose would misrepresent both. 05_CALC labels every window explicitly. Either state both windows or do not draw the comparison.
A8: No sampling error is reported anywhere | B8: The Eurostat, Nationalbank and Agency for Digital Government figures are survey estimates and carry sampling error that the issuing authorities publish but this workbook does not reproduce. Small differences should not be treated as established: a 2-3 point gap between two survey proportions, or between two eGovernment Benchmark scores, may not be distinguishable from zero. Directions are more robust than magnitudes throughout.
A9: Headcount conversions rest on an implied denominator | B9: A published figure for the Danish population aged 15 and over could not be verified in this session. F4 therefore derives an implied 15+ base by dividing the exempt headcount by the exemption rate, both from the same source. Persons-affected figures built on it are orders of magnitude, not counts, and the capability shares they scale are measured on 'the population' rather than on the 15+ base - the denominators are not identical. Every such cell is marked in place.
A10: A withdrawn claim about SMV:Digital | B10: An earlier draft of this workbook asserted that SMV:Digital was being defunded, and an argument was built on the contrast between a programme that works and a programme being cut. The claim could not be verified. The scheme's own 2026 grant-pool page documents pools still open and a further pool opening on 26 October 2026. The claim has been removed from the dataset and from the report's argument, and the correction is recorded in 09_POLICY and 08_AI_LOG rather than silently erased.
A11: Unbalanced panel | B11: Observation years differ by series because the underlying sources publish on different cycles - payment habits roughly biennially, Eurostat annually, branch counts irregularly. Gaps are genuine and are not filled.
A12: Denominator break | B12: Danish online-purchasing figures change base between 2019 (% of individuals) and 2020 onward (% of internet users). The 2019 observation carries flag 'b' and is never plotted with later years.
A13: Verbal quantities | B13: Values flagged 'e' were published as words, not figures - 'nearly one in five', 'just under 36,000'. They are recorded as the stated approximation with the original wording in the notes column.
A14: Confounded outcome | B14: Branch closures reflect both digitalisation and sectoral consolidation (219 institutions in 1991, 51 in 2024). The branch series alone cannot separate these, and the report should not claim that it does.
A15: Definitional spread in exclusion measures | B15: The five exclusion measures range from 4.7% to 25% because they define the population differently. They are not competing estimates of one quantity and must not be averaged or presented as a range.
... A21: Discarded material | B21: An earlier candidate dataset was rejected in full after verification found fabricated values carrying authentic dataset codes and extraction dates - including a Eurostat cross-section that inverted the true EU country ranking. None of it survives in this workbook.

Sheet 08_AI_LOG
A1: AI use and validation log
A2: Raw material for the AI Use and Validation Appendix.
A4: step | B4: AI assistance used | C4: how it was validated | D4: outcome
A5: Source identification | B5: AI used to identify candidate statistical sources and dataset codes. | C5: Each source opened or search-verified against the issuing authority. | D5: Source register in 03_SOURCES.
A6: Value retrieval | B6: AI used to search for published values by authority and indicator. | C6: Each value checked against a result reporting the issuing authority's own publication. | D6: Every retained observation carries a source_id.
A7: Rejection of a prior dataset | B7: A candidate dataset produced with AI assistance was reviewed. | C7: Cross-checked against Eurostat's published country ranking; the values inverted the true ranking and contained duplicated and interpolated cells. | D7: Dataset rejected in full and excluded.
A8: Withdrawal of an AI-suggested claim | B8: An AI-assisted draft asserted that the SMV:Digital grant scheme was being defunded, and an argument was built on the contrast between a programme with measured positive effects and a programme being cut. | C8: Searched for the scheme's funding status. The scheme's own 2026 grant-pool page documents pools still open and a further pool opening 26 October 2026. No source supported the defunding claim. | D8: Claim withdrawn from the dataset and the argument; the withdrawal is recorded in 09_POLICY and 07_LIMITATIONS rather than erased.
A9: Statistical self-audit | B9: AI was asked to audit its own workbook as a macroeconomic policy reviewer would. | C9: The audit found that Figure 6's adoption column had been assembled from a press release naming only the top three, bottom three and three large movers - a sample drawn from the tails, which inflates R-squared by construction. | D9: R-squared removed from the chart face; a selection warning added to F6; the limitation recorded in 07_LIMITATIONS. Later resolved - see the two rows below.
A10: Failed verification attempt | B10: AI was asked to retrieve Eurostat isoc_ec_ib20 for 2024 for the twelve member states missing from Figure 6, so the tail selection could be removed. | C10: Eurostat and the national statistical offices are unreachable from the build environment. Web search returned only the press release naming the same tails, two country values with no attributable source, and one answer mixing the '% of internet users' and '% of individuals' denominators in a single paragraph. | D10: No values accepted. Recorded because the honest outcome of a verification attempt is sometimes that it failed.
A11: Author-supplied authoritative extract | B11: The author retrieved the complete isoc_ec_ib20 table from the Eurostat databrowser and supplied it as a spreadsheet; AI parsed it into the dataset. | C11: The extract carries its own provenance header - dataset code, extraction timestamp, last-update date, and an explicit unit of 'percentage of individuals who used internet within the last year'. The ten values it overlapped with were compared against the rounded press-release figures already held; all ten agreed to rounding. | D11: All 27 member states plus the EU-27 aggregate added under source ES7. Figure 6 went from n=6 to n=18 and R-squared was restored to the chart face. The superseded rounded values are recorded in each row's note.
A12: Workbook construction | B12: AI wrote the Python build script that generates this workbook. | C12: Structural assertions run at build time: source_ids resolve, units and denominators present, no duplicate observations, break flags set. | D12: build_workbook.py, re-runnable.
A13: Analytical framing | B13: AI used to interpret patterns and suggest framings. | C13: Author reviewed each interpretation against the underlying values. | D13: Interpretations appear in the report, attributed to the author.
A14: Not delegated to AI | B14: Selection of the research question, country, industries, SDG and policy comparator; the argument; the conclusions. | C14: n/a | D14: Author's own work.
A16: This log records assistance during data assembly. Complete it with any further AI use during drafting before submission. The assessment requires that AI-assisted content be verified and acknowledged.

Sheet 09_POLICY
A1: Policy events
A2: Dated instruments, with the series each one bears on. Rendered as event tables beneath the figures they affect.
A4: date | B4: precision | C4: instrument | D4: legal citation | E4: source_id | F4: what it does | G4: series affected
A5: 2012-06-11 | B5: day | C5: Lov om Offentlig Digital Post adopted | D5: LOV nr 528 af 11/06/2012 | E5: RI1 | F5: Creates the statutory basis for mandatory public digital post. Section 10 deems delivery effective on availability, not on the message being read. | G5: DK.DGP.EXMP
A6: 2013-01-01 | B6: year | C6: Digital Post becomes mandatory for businesses | D6: Lov om Offentlig Digital Post | E6: DG4 | F6: Businesses are enrolled a year ahead of citizens. | G6: DK.ECM.ENT.TRN
A7: 2014-11-01 | B7: day | C7: Digital Post becomes mandatory for citizens aged 15+ | D7: Lov om Offentlig Digital Post | E7: DG4 | F7: Citizens are enrolled automatically whether or not they registered themselves. Exemption is available only against statutory criteria. This is the single most consequential date in this workbook. | G7: DK.DGP.EXMP
A8: 2016-01-01 | B8: month | C8: Rigsrevisionen reports on the Digital Post business case | D8: Beretning, January 2016 | E8: RR1 | F8: Of an approx. DKK 1bn projected annual saving, only DKK 450m - postage, paper and envelopes - could be verified. | G8: DK.GOV.DGP.SAVE.PLAN
A9: 2018-01-01 | B9: year | C9: SMV:Digital launched | D9: Danish digital growth plan for SMEs | E9: DG3 | F9: Grant scheme subsidising SME digitalisation projects. | G9: DK.SME.SMVD.PROJ
A10: 2021-10-01 | B10: month | C10: MitID rollout begins | D10: National electronic ID replacement programme | E10: DG4 | F10: Begins the migration of the whole population off NemID. | G10: DK.TRU.DPS
A11: 2022-07-01 | B11: day | C11: Kontantreglen amended | D11: Lov om betalinger, ss 81 | E11: RI2 | F11: Businesses may refuse cash from other businesses; temporary events are exempted; the notification duty for 06:00-20:00 acceptance is removed. The obligation on shops to accept cash from consumers remains. | G11: DK.PAY.CASH.POS
A12: 2022-09-22 | B12: day | C12: MitID required for public digital services | D12: National electronic ID replacement programme | E12: DG4 | F12: From this date citizens need MitID for borger.dk, skat.dk and sundhed.dk. | G12: DK.TRU.DPS
A13: 2023-10-31 | B13: day | C13: NemID fully phased out | D13: National electronic ID replacement programme | E13: DG4 | F13: The predecessor credential can no longer be obtained or used. | G13: DK.TRU.DPS
A14: 2026-01-01 | B14: year | C14: SMV:Digital grant pools continue | D14: Tilskudspuljer i 2026 | E14: SMV1 | F14: The scheme is still operating and still awarding grants in 2026; a further pool opens on 26 October 2026. Recorded because an earlier draft of this workbook asserted the scheme was being defunded. It was not verifiable and the opposite is documented. | G14: DK.SME.SMVD.PROJ
A16: Reading: the mandate date of 1 November 2014 is the hinge of this workbook. Digital Post was not adopted by citizens choosing it; citizens were enrolled automatically, and exemption is available only against statutory criteria. Adoption rates after that date therefore measure compliance with a legal obligation, not revealed preference, and no figure in this workbook should be read as though they measured preference.
A18: CORRECTION RECORDED: an earlier draft of this workbook stated that SMV:Digital was being defunded. That claim could not be verified, and the scheme's own 2026 grant-pool page (SMV1) documents pools still open, with a further pool opening on 26 October 2026. The claim has been withdrawn from the dataset and from the report's argument. See 07_LIMITATIONS and 08_AI_LOG.
